{"001YG": 2, "00607": 2, "00HFP": 1, "00MFE": 1, "00N38": 1, "00T1E": 1, "00X3U": 1, "00YZL": 3, "00ZCA": 2, "013SD": 1, "01K8X": 1, "01KML": 1, "01THT": 2, "01ZWG": 2, "024PD": 2, "02CYP": 3, "02DPI": 4, "02SK4": 2, "02SKC": 2, "02XLP": 1, "03AA8": 2, "03M0K": 1, "03OQS": 1, "03PRW": 4, "03XSP": 2, "04LAX": 1, "05WY6": 1, "06CKN": 2, "06LBQ": 1, "06NUT": 1, "06OKE": 2, "06X2V": 2, "07LG5": 2, "07QNG": 4, "07TCM": 2, "08F85": 1, "08KKF": 1, "08QQS": 1, "099Y1": 4, "09AT0": 3, "09W8V": 1, "0A8ZT": 2, "0AGCS": 1, "0AMBV": 1, "0BLSL": 1, "0BNML": 2, "0BWYH": 1, "0BX9N": 1, "0BXRP": 2, "0BZAD": 2, "0C5IQ": 1, "0CESB": 1, "0CFQV": 1, "0CG15": 2, "0CQL8": 2, "0CX32": 2, "0DD62": 1, "0EGNU": 5, "0EJAG": 2, "0ETKN": 1, "0F0WE": 2, "0F1VF": 1, "0F453": 1, "0FC0N": 3, "0FJSU": 1, "0FVYR": 2, "0G2SC": 2, "0GH5O": 2, "0GR11": 1, "0GYRH": 2, "0H04V": 1, "0H5VC": 3, "0HGNK": 2, "0HVVN": 2, "0I0FX": 2, "0I1S5": 2, "0IAGO": 2, "0IFCL": 1, "0J1AQ": 4, "0J5T4": 2, "0JA9E": 2, "0JB3D": 2, "0JJIY": 1, "0JXN3": 1, "0K0LP": 2, "0KZYF": 2, "0LDN3": 1, "0LHWF": 3, "0M1X0": 1, "0M1ZU": 1, "0M6IY": 2, "0M7YH": 1, "0M9ZO": 2, "0MDYC": 1, "0MFAM": 1, "0N8OZ": 1, "0NM06": 1, "0NVG2": 3, "0NZVB": 2, "0O022": 1, "0O36O": 1, "0O6RK": 2, "0OE6M": 1, "0OMFD": 1, "0OSJY": 1, "0OUEP": 2, "0PA3N": 1, "0POYO": 1, "0PPPL": 3, "0PSL4": 1, "0PU21": 2, "0PVKV": 5, "0QES3": 1, "0QHR4": 2, "0QMGP": 1, "0R4UI": 1, "0R5GS": 1, "0RNG6": 2, "0RNRI": 2, "0RP6B": 2, "0RPJX": 2, "0RSFD": 2, "0S9KN": 1, "0SBT3": 1, "0SE6A": 1, "0SXRS": 2, "0TDOP": 3, "0TIHC": 3, "0TKKR": 5, "0TM53": 2, "0TXYV": 2, "0UFGC": 1, "0UK3H": 1, "0UQU6": 1, "0VOQC": 2, "0VQCH": 1, "0VQES": 2, "0VQQL": 2, "0W39H": 3, "0WYBK": 4, "0XB7U": 1, "0XV4T": 2, "0XV7B": 4, "0Y19Q": 2, "0YTSJ": 5, "0Z1PC": 6, "0Z36L": 2, "0ZOPH": 1, "0ZSFI": 2, "106AY": 3, "107YZ": 1, "10AEA": 1, "10INO": 9, "10LP3": 1, "10ND1": 1, "113YU": 1, "119W9": 1, "11DD3": 2, "11TTU": 2, "120YL": 3, "1221S": 1, "129SP": 2, "12VVC": 1, "132HR": 1, "1333C": 2, "136V6": 3, "13IJA": 1, "13IS9": 1, "13MWT": 1, "13XM4": 3, "13YII": 3, "1440M": 2, "151DU": 1, "15PMU": 3, "15RTV": 3, "165K2": 1, "16IDQ": 2, "16OAM": 1, "16UNJ": 1, "170OQ": 5, "17AZ5": 2, "17LNN": 1, "17P5V": 1, "17RPG": 1, "186EF": 1, "18FTZ": 3, "194WK": 2, "19BHU": 1, "19PNV": 1, "19SJ6": 1, "19ZGX": 2, "19ZJB": 2, "1AA3I": 1, "1B2P0": 2, "1B9DK": 1, "1BBIY": 2, "1BGZ0": 2, "1BUFQ": 2, "1C6P3": 2, "1DNAX": 1, "1E1EN": 4, "1E7VU": 2, "1ECM2": 1, "1EJKT": 1, "1F4JZ": 2, "1F4YB": 1, "1FA5M": 2, "1FGXJ": 2, "1FIGA": 2, "1FPW9": 2, "1G2QC": 2, "1G90H": 1, "1GGRY": 2, "1GII3": 3, "1H6PS": 2, "1HAYV": 5, "1HGEX": 2, "1HL2K": 1, "1HZGH": 2, "1IIS5": 3, "1IPYC": 2, "1J3I0": 2, "1JYPW": 2, "1K0SU": 3, "1K4ZT": 2, "1KDFH": 1, "1KJI0": 2, "1KKYX": 1, "1L5D3": 2, "1L7XE": 1, "1LARL": 3, "1LKPL": 1, "1MD1H": 3, "1MU5L": 1, "1MZJF": 2, "1NNFV": 2, "1NVWD": 2, "1O1JS": 2, "1O6PH": 1, "1OIPY": 2, "1PALI": 1, "1PB6T": 1, "1Q5ST": 1, "1QP1S": 4, "1R9XW": 3, "1RD2K": 2, "1RHDP": 1, "1RNK6": 1, "1SCZE": 1, "1SJQX": 2, "1SLTT": 1, "1SMZZ": 2, "1SVJS": 1, "1T2W4": 1, "1TAMK": 1, "1TIAK": 1, "1TW98": 1, "1TZK5": 2, "1UHL7": 3, "1UI6I": 1, "1US0H": 1, "1UXVA": 2, "1VF27": 3, "1VMZM": 1, "1VRH1": 2, "1VUDV": 1, "1W28T": 1, "1W6YY": 1, "1W6ZK": 2, "1WEDJ": 3, "1WJ6O": 4, "1WWJZ": 1, "1X0M3": 1, "1X4SD": 1, "1X765": 3, "1X9A1": 2, "1XOQ8": 1, "1YAYG": 3, "1YC83": 2, "1YH1Y": 1, "1YSGI": 2, "1YTD7": 1, "1Z5FK": 2, "1ZBM9": 2, "1ZBUS": 2, "2074D": 1, "20LDB": 1, "20WZU": 2, "21A0W": 3, "21F9H": 3, "21MI8": 1, "21WN7": 6, "22A2G": 1, "22ROE": 2, "23X63": 1, "23Y3I": 1, "23YS1": 1, "2443O": 2, "24B2K": 3, "24XHS": 2, "250SN": 1, "2544C": 3, "25QPB": 2, "25YVM": 1, "268ET": 1, "26JZM": 1, "26RQN": 1, "275W0": 2, "27DCQ": 1, "27JQL": 3, "27SS2": 1, "27ZT9": 2, "282ZZ": 1, "2846J": 1, "287ST": 2, "293PC": 1, "297S4": 2, "29C6X": 1, "29LL7": 1, "29T54": 2, "2AG8W": 1, "2AIP4": 5, "2B3BL": 3, "2B577": 2, "2B8ML": 1, "2BO2G": 3, "2BS0V": 2, "2BUDH": 2, "2C253": 2, "2D98B": 1, "2DDGF": 4, "2DO31": 1, "2DPW0": 2, "2DTZ3": 1, "2ECXI": 1, "2EPFZ": 2, "2FC4V": 2, "2FH2V": 1, "2FLXE": 1, "2FPB3": 1, "2FW38": 3, "2G59W": 1, "2GF6R": 2, "2GQDN": 4, "2H56B": 1, "2H9YB": 1, "2I871": 1, "2IS9G": 1, "2J4MA": 1, "2JP64": 4, "2JR26": 1, "2JTRG": 4, "2JWHI": 1, "2KGV3": 5, "2KMGY": 2, "2L6E2": 2, "2LCLG": 2, "2LMQF": 5, "2M2O6": 2, "2M9YL": 2, "2MGC1": 1, "2MJ72": 1, "2MR5K": 1, "2MTYU": 1, "2MURI": 1, "2NV6L": 1, "2O6RB": 2, "2ODLD": 1, "2OJY8": 1, "2OWA8": 2, "2OY8R": 2, "2P6ZP": 2, "2P7A9": 3, "2PREF": 2, "2Q2LA": 1, "2Q3ZJ": 2, "2Q5Y2": 1, "2Q6SZ": 1, "2QI8F": 1, "2QWGI": 1, "2QYZA": 1, "2RFLZ": 1, "2RRSO": 2, "2RTH2": 2, "2SKOA": 1, "2SQ8M": 1, "2SYBS": 1, "2TAT3": 1, "2TBSE": 1, "2TU40": 4, "2U0QT": 2, "2UQKZ": 2, "2UXXB": 1, "2VNXF": 2, "2WGSN": 1, "2WX2Z": 1, "2XG25": 1, "2XSK6": 2, "2XVR0": 4, "2YJUQ": 3, "2Z8HO": 1, "2ZFNL": 2, "2ZG3U": 1, "2ZICJ": 4, "2ZXJ5": 1, "3064K": 2, "306S9": 2, "30I35": 2, "30LGT": 2, "30PG2": 2, "313G8": 1, "318CP": 4, "31LW5": 1, "31YNM": 3, "320VL": 2, "320ZB": 1, "327L5": 1, "32MUM": 1, "330ZE": 1, "337O2": 2, "33OVO": 2, "34IUI": 1, "34J80": 1, "34OT4": 4, "358JF": 3, "35C4E": 1, "35ZZP": 4, "36AJ1": 2, "36T5X": 4, "36VYU": 2, "3731F": 3, "386XM": 1, "38I4G": 2, "38NUC": 3, "38ZFZ": 1, "391VK": 1, "39850": 1, "39LQ8": 1, "3AE3T": 1, "3AEF5": 2, "3AKML": 1, "3APWC": 1, "3AVAH": 2, "3B81O": 2, "3B97C": 1, "3BH39": 1, "3C1ZN": 2, "3C36H": 2, "3C8OG": 4, "3C9L1": 2, "3CAPI": 1, "3CFFJ": 4, "3CKXF": 1, "3CLVI": 3, "3CW6P": 2, "3D94R": 1, "3DLKC": 4, "3DO95": 2, "3DUAO": 2, "3EDV7": 1, "3EIRZ": 2, "3EJQW": 1, "3EYLH": 1, "3FEYY": 2, "3G1OQ": 1, "3G4PN": 1, "3G991": 5, "3GA59": 1, "3GFIC": 2, "3GNH7": 1, "3GXB7": 1, "3GY40": 3, "3H0PT": 2, "3H1EA": 1, "3HLP7": 2, "3HOJR": 1, "3IAPG": 2, "3IJGQ": 3, "3IMTV": 2, "3IPI3": 2, "3IRHH": 2, "3J639": 1, "3JCEI": 3, "3JJ7C": 2, "3JSX7": 1, "3JXKZ": 2, "3K2QE": 2, "3K6HO": 1, "3KZF7": 2, "3L3LC": 2, "3LFV6": 1, "3LIGG": 1, "3LLDC": 1, "3LM6H": 2, "3LMTS": 1, "3MLVF": 1, "3MWAY": 2, "3MX8V": 1, "3N1I2": 2, "3ND23": 3, "3NKHT": 2, "3O6KD": 2, "3OAGK": 1, "3OLX3": 3, "3ONCH": 1, "3OQ8M": 2, "3OUXT": 4, "3OZUX": 2, "3P8NL": 1, "3PTQK": 1, "3PXGQ": 2, "3Q3YY": 2, "3Q6N1": 2, "3Q92U": 1, "3QGLU": 1, "3QL7J": 2, "3R4DD": 3, "3RSJV": 2, "3SAO5": 2, "3SDJE": 1, "3SNSC": 1, "3T785": 2, "3TK88": 1, "3TUUI": 1, "3TV9E": 1, "3UZ88": 1, "3V2HJ": 1, "3V7X2": 1, "3VM0R": 2, "3VMTS": 1, "3VRTT": 1, "3VT73": 4, "3VWSP": 1, "3VYGU": 1, "3W1GP": 4, "3W31X": 1, "3W5GB": 1, "3W6CP": 1, "3W6TL": 1, "3WAWR": 2, "3WMV4": 2, "3X52E": 2, "3XKBC": 2, "3XL0K": 1, "3XM7Q": 1, "3YC35": 3, "3YNPY": 1, "3YVPG": 3, "3YY88": 1, "3Z1YC": 2, "3Z7KH": 2, "3ZC4Y": 2, "3ZH9Z": 2, "3ZOI4": 2, "4021N": 1, "40309": 1, "409X2": 2, "40DSU": 1, "40F42": 1, "40TYU": 2, "40WPV": 2, "417RA": 1, "41CZS": 2, "41EQS": 3, "41II2": 2, "41T8C": 2, "422BV": 2, "428VQ": 2, "42E9I": 1, "42MC3": 1, "42PMR": 3, "432NL": 2, "43CCM": 2, "43FG9": 1, "43OXO": 3, "43UGG": 3, "448J4": 3, "44PFW": 2, "44Q8A": 2, "44Y6S": 2, "450TW": 3, "45D5U": 1, "45FWP": 1, "45P7D": 2, "45Z2A": 1, "4683D": 1, "46Z16": 2, "472EJ": 1, "47I6H": 1, "47RAA": 3, "47ZXN": 2, "493WS": 1, "49QXY": 1, "4A81E": 2, "4ALLQ": 2, "4BEZX": 4, "4BGWL": 1, "4BSR0": 1, "4BZI6": 2, "4C1KY": 5, "4C4LC": 2, "4C5S6": 1, "4CAB5": 2, "4CAHN": 1, "4CHXK": 1, "4DZ33": 1, "4DZB6": 1, "4EM25": 1, "4F76V": 2, "4FAWP": 1, "4FS34": 1, "4FX6G": 2, "4FXUI": 1, "4G00A": 3, "4G3ZF": 1, "4GCPM": 1, "4GDTQ": 1, "4GLAP": 2, "4H61U": 1, "4H64T": 2, "4H935": 3, "4HFN2": 1, "4I00F": 3, "4JOAD": 2, "4JW8U": 1, "4JWAH": 3, "4JXAK": 1, "4KK20": 3, "4KOBZ": 3, "4KYZH": 1, "4L664": 2, "4L6GZ": 2, "4LU0G": 2, "4MFE0": 3, "4MUXJ": 2, "4N5P9": 2, "4NIBA": 1, "4NRPM": 1, "4P13T": 2, "4PCSC": 3, "4QSRS": 1, "4RBVB": 2, "4RKKP": 2, "4RLYA": 2, "4RT06": 3, "4S3UZ": 1, "4SGC9": 1, "4TX4N": 6, "4U52R": 2, "4U8WV": 1, "4UT8K": 2, "4UXE3": 2, "4UYGY": 1, "4VCHD": 2, "4VODV": 2, "4WO5F": 1, "4WUNC": 2, "4WX0H": 1, "4X2JC": 2, "4X5P6": 1, "4Y1AW": 3, "4Y8FU": 1, "4YBN9": 1, "4YL07": 2, "4Z3PQ": 2, "4ZJXR": 5, "4ZN66": 2, "4ZRHH": 1, "4ZY8C": 2, "50E06": 5, "511AM": 2, "51801": 3, "51N2C": 2, "52CKM": 1, "52D5Q": 1, "52FNN": 2, "52MV9": 4, "52QLH": 2, "52WDV": 1, "5311V": 1, "539EH": 3, "541JP": 1, "54VBR": 4, "555RO": 3, "55687": 3, "55AH5": 1, "55BOW": 3, "55FRY": 2, "55NNF": 1, "55NRK": 2, "55OAL": 1, "55V6Z": 2, "564DX": 3, "5657O": 2, "56PK0": 2, "56XKK": 3, "573OJ": 2, "5776I": 1, "57A1A": 1, "57MEO": 1, "57QQ7": 2, "57RY4": 1, "57WV7": 2, "57WXL": 2, "580G0": 1, "58VZI": 2, "58YA5": 1, "58Z9R": 2, "59KH0": 3, "59X8N": 3, "5A3FT": 3, "5ACD3": 1, "5AE54": 2, "5AFC1": 1, "5AM4C": 1, "5AW54": 1, "5B8M5": 1, "5B9XE": 1, "5BQMX": 2, "5C4EK": 2, "5C6IS": 1, "5C837": 1, "5CZRC": 1, "5D351": 3, "5D85P": 1, "5DJ3S": 3, "5EDX4": 2, "5EEFP": 2, "5EEXF": 3, "5EFVR": 2, "5EFZ1": 1, "5F1AW": 1, "5FDHU": 1, "5FHH2": 1, "5GEJS": 1, "5GG5W": 1, "5GHV3": 2, "5GITI": 1, "5GK8W": 4, "5GP8M": 3, "5GPOJ": 2, "5GWS2": 2, "5H1P1": 1, "5HGHH": 1, "5HOAV": 2, "5HPZ1": 5, "5HSKK": 2, "5I330": 1, "5I4UT": 1, "5IDF4": 2, "5INX3": 3, "5IPJA": 3, "5IVO1": 2, "5IW8A": 2, "5JIGM": 2, "5JSFE": 2, "5K0KJ": 1, "5KGCY": 1, "5KOTU": 1, "5L09N": 3, "5LTLL": 2, "5M17J": 4, "5MF9Y": 2, "5MG4A": 1, "5NG6Q": 1, "5NK4L": 1, "5NV2Z": 2, "5O281": 2, "5O31N": 1, "5OB3W": 3, "5OIQ7": 2, "5OLVC": 2, "5OV3M": 4, "5P0ON": 2, "5P284": 3, "5Q0CX": 1, "5QJNP": 1, "5QUSB": 2, "5QW1X": 1, "5QXCO": 1, "5R8BL": 2, "5S1WQ": 1, "5S587": 1, "5SAAB": 2, "5SBEY": 1, "5T0NX": 1, "5T607": 2, "5TNRZ": 1, "5U92L": 1, "5UFCJ": 2, "5UNMN": 1, "5V5EL": 1, "5V8WH": 1, "5VDT6": 2, "5VINT": 1, "5VS8B": 1, "5VUQE": 1, "5VUT9": 2, "5W0OC": 2, "5W1Z7": 1, "5X039": 4, "5X5DT": 3, "5XA4R": 1, "5XAFE": 1, "5XAMJ": 2, "5XCJ6": 3, "5XCUV": 1, "5XKVP": 2, "5XLBY": 1, "5YN7H": 1, "5Z1CO": 1, "5ZDNU": 1, "5ZGRN": 2, "5ZHOX": 2, "5ZHUE": 1, "5ZRFL": 1, "5ZXA3": 2, "61IVZ": 2, "61UIO": 3, "61WIS": 2, "61XR6": 2, "622EX": 1, "62AC0": 2, "63TU2": 1, "64F1C": 4, "64HO1": 2, "64IAU": 1, "65UVU": 2, "6703W": 2, "67MSU": 2, "67RSR": 1, "68K01": 2, "68OG0": 3, "68YR6": 1, "6912B": 2, "696GE": 1, "69F8P": 2, "69GFN": 1, "69R8T": 3, "6AHBW": 3, "6AHD0": 3, "6ALEL": 2, "6B2FN": 1, "6B328": 2, "6B7HM": 2, "6B93R": 1, "6BI70": 2, "6BUU6": 1, "6C2DJ": 2, "6C4DV": 2, "6C65Z": 1, "6CAZU": 3, "6EU06": 3, "6F5W0": 3, "6FJBD": 4, "6FUDS": 1, "6FV5P": 2, "6FYKZ": 1, "6FYXS": 2, "6H78U": 3, "6HT0J": 3, "6IHRD": 2, "6IL0C": 3, "6J8NE": 1, "6JB9M": 1, "6JGXL": 1, "6JLD4": 2, "6KDQO": 3, "6KGZA": 1, "6KI0S": 4, "6KIA4": 1, "6KJGX": 1, "6LBDM": 3, "6LNYW": 1, "6LUM5": 1, "6MCD9": 1, "6MH42": 1, "6N2ZB": 2, "6N7G6": 3, "6NWDR": 1, "6OQYV": 2, "6OROW": 3, "6PL9Z": 1, "6PQZE": 2, "6PYRZ": 1, "6PZJ3": 2, "6QDZI": 2, "6QSON": 2, "6R7QW": 3, "6R7QY": 1, "6RPUS": 1, "6RQHP": 1, "6RXCP": 1, "6SWTR": 1, "6SY23": 2, "6TJVS": 6, "6TNP4": 2, "6TV29": 2, "6TVXT": 2, "6U082": 1, "6UDGS": 2, "6UMSJ": 2, "6VF2L": 2, "6VUKN": 3, "6W82I": 1, "6WWB3": 2, "6WZ1K": 2, "6XGUE": 4, "6YGBD": 5, "6YH19": 2, "6YN3J": 3, "6YTAJ": 4, "6YZOL": 1, "6YZQO": 1, "6ZJAL": 2, "6ZKZS": 2, "6ZSB2": 1, "6ZWSU": 3, "70PUI": 1, "70S6Y": 1, "70SEI": 1, "70TVS": 3, "7177T": 3, "71QKB": 1, "727IZ": 3, "72HTA": 2, "72LJ3": 3, "72R6A": 1, "72VJD": 2, "7326A": 1, "735W9": 2, "73E7V": 4, "73NG4": 3, "73XDD": 2, "74DPG": 6, "74GN1": 1, "74P3C": 1, "74WSB": 3, "759MY": 2, "75AX5": 3, "75GKF": 1, "75KQ6": 2, "75M1Z": 1, "75MO8": 3, "75RPN": 2, "75ZOJ": 3, "76BFU": 1, "76TOK": 3, "76Z3W": 2, "77JB7": 1, "77JGY": 5, "77SCM": 1, "77UTO": 5, "77Z0Z": 2, "7835X": 2, "785X2": 4, "78R4Y": 2, "78SO8": 1, "78XRT": 2, "78XZ9": 1, "79VVK": 4, "79WPY": 1, "7AB3X": 1, "7ARCD": 1, "7B1CR": 2, "7B3J0": 2, "7B50N": 2, "7B6FP": 2, "7B8EQ": 1, "7BX06": 3, "7CCM1": 1, "7CXYB": 2, "7D99X": 2, "7DGWM": 3, "7DZY6": 1, "7E6AB": 1, "7EJUR": 2, "7ELBG": 3, "7FAB3": 1, "7FCAW": 1, "7FQ5Q": 1, "7FTBS": 3, "7FTZR": 1, "7G0HB": 1, "7G6F0": 1, "7GYR4": 1, "7H0JK": 2, "7HEWH": 2, "7HLTQ": 1, "7HSZJ": 1, "7HVU8": 1, "7HWS7": 1, "7JDU4": 1, "7JSAI": 2, "7JTEK": 4, "7JZGN": 3, "7JZTY": 2, "7K9XM": 7, "7KAVM": 3, "7KHIH": 1, "7L0TN": 2, "7L2RT": 1, "7L4DW": 1, "7L5W3": 1, "7L7P4": 1, "7LWW3": 4, "7LYA9": 1, "7M1D0": 1, "7MRKY": 2, "7NBPG": 1, "7NW4V": 1, "7NXWU": 3, "7ODVS": 1, "7OXNH": 1, "7P5R2": 2, "7POUA": 3, "7QWL3": 1, "7R4YS": 1, "7RI1Y": 1, "7SAFU": 2, "7SNIO": 1, "7SXQS": 2, "7T6MB": 1, "7TA23": 2, "7TJ14": 2, "7U9EW": 1, "7UGF7": 3, "7UPGT": 1, "7UQFM": 2, "7UV4O": 1, "7V4NJ": 2, "7VHXG": 1, "7VP2U": 3, "7W1ZI": 1, "7W8E0": 1, "7WG7A": 1, "7WIKW": 3, "7WIRG": 1, "7WJUW": 3, "7XKUI": 1, "7XMBM": 1, "7XNAI": 1, "7YMK9": 1, "7YV59": 1, "7Z69Y": 5, "7ZCXJ": 2, "7ZL8E": 3, "7ZUE1": 1, "803H6": 2, "808H5": 1, "80E3X": 3, "80FWF": 1, "80YWL": 1, "815KV": 1, "8175C": 1, "81NAT": 1, "81QUM": 1, "81R3C": 2, "81R72": 1, "81YF0": 1, "81YUE": 1, "827O1": 1, "82B2V": 2, "82R7V": 3, "82XWA": 3, "82YF1": 2, "82ZNR": 2, "830OE": 1, "83654": 3, "83D9H": 1, "83JOK": 1, "83S5W": 3, "83V0A": 2, "83XF0": 1, "84893": 2, "857LD": 1, "85ABO": 1, "85LEB": 2, "85OEC": 1, "866F1": 1, "869NM": 2, "86E2E": 2, "86GSE": 1, "86X97": 2, "87T5P": 1, "87Y64": 2, "884C0": 1, "88CD5": 1, "88LYX": 1, "88TGX": 1, "88ZT4": 3, "89MAO": 1, "8AKGE": 2, "8APDH": 1, "8ASRQ": 1, "8ATVC": 1, "8AZRX": 2, "8BBX0": 1, "8BCI8": 1, "8BMZQ": 1, "8BNUT": 1, "8BSG7": 1, "8C8FI": 1, "8CCEV": 2, "8CJML": 2, "8DL54": 2, "8DSGI": 2, "8E5AD": 1, "8EKYA": 1, "8ENLP": 4, "8EU89": 2, "8FH96": 1, "8FP8X": 2, "8G9A9": 3, "8GXNA": 2, "8HHI3": 2, "8ICEM": 4, "8IDIY": 1, "8IPWO": 1, "8ISS6": 1, "8J2K5": 1, "8J5O9": 2, "8J723": 2, "8JMY5": 1, "8JR94": 2, "8JT6S": 1, "8L08M": 1, "8L9AJ": 1, "8LAK1": 1, "8LPZ0": 1, "8LVCL": 2, "8LWV7": 1, "8M1TG": 1, "8MDSA": 2, "8ML3S": 2, "8MLCU": 1, "8MQH6": 1, "8MX1T": 1, "8MY8P": 1, "8N4O9": 2, "8N7NZ": 2, "8N939": 2, "8NDRG": 2, "8NGDR": 3, "8NS1G": 2, "8NW4J": 2, "8OHDL": 1, "8PL34": 2, "8PRDP": 1, "8PSXZ": 1, "8QCBP": 2, "8QWE4": 3, "8RFDF": 1, "8RU1Q": 3, "8SA46": 2, "8SDK5": 1, "8SVWO": 4, "8SXHK": 2, "8TDNF": 1, "8TSH9": 1, "8TSU4": 1, "8U5TE": 2, "8UCK1": 2, "8UUUR": 1, "8V8HC": 1, "8V97G": 1, "8V9IX": 3, "8VDZ7": 2, "8VNSV": 2, "8VSV6": 1, "8VVHR": 2, "8VWV2": 2, "8W0XJ": 1, "8W31Y": 1, "8WQOP": 2, "8XC4G": 2, "8XFAV": 2, "8XJP7": 2, "8XL11": 1, "8XXNK": 2, "8YD0O": 5, "8YFD1": 2, "8YK8Y": 2, "8YKGP": 1, "8YNSB": 2, "8YZ8X": 1, "8Z02S": 1, "8Z9GW": 1, "8ZO48": 2, "901GH": 2, "909RL": 1, "91YZH": 2, "9207X": 1, "92FFB": 1, "92NRK": 2, "92Q8F": 1, "92QGQ": 3, "92UB5": 2, "92WXO": 1, "9335E": 4, "937EW": 1, "93EOJ": 1, "93HQR": 1, "93REJ": 4, "94HB1": 2, "94HXT": 1, "94ICP": 1, "94KP4": 1, "94LXD": 2, "94YTY": 2, "95GB4": 1, "9632M": 1, "969Z9": 1, "96ATI": 3, "96GIQ": 1, "97086": 2, "974TA": 1, "97HAH": 2, "97NNW": 1, "97Y6T": 2, "983K8": 3, "987P8": 2, "98W87": 3, "99596": 1, "999BP": 2, "99B6U": 2, "99SGB": 1, "99UA6": 2, "99XHN": 1, "9A58F": 1, "9A90E": 1, "9AC1T": 1, "9AFQ7": 6, "9AFSH": 1, "9B93K": 3, "9BCZU": 2, "9BPW6": 3, "9C5PT": 1, "9D2T4": 1, "9D6WC": 1, "9EEGQ": 2, "9EP7R": 2, "9F691": 1, "9FBAP": 1, "9FH1E": 3, "9FHVW": 1, "9FVR3": 3, "9GMHF": 1, "9GQRI": 2, "9GS13": 2, "9HNRY": 2, "9HOV3": 2, "9ILM6": 2, "9IT59": 1, "9IY50": 2, "9J0RB": 2, "9J166": 1, "9JIOI": 1, "9JPV3": 1, "9JZO2": 3, "9K2TY": 1, "9KDP0": 2, "9KGOL": 2, "9LHP3": 2, "9LO9F": 2, "9LWQ6": 2, "9M48H": 1, "9M5UE": 4, "9MNZ5": 7, "9MXDX": 3, "9N0BP": 2, "9N76L": 2, "9NES7": 1, "9NRLA": 1, "9NV2G": 1, "9NWSD": 1, "9O0HH": 1, "9O0NP": 2, "9OCQT": 1, "9OEWM": 1, "9OH7W": 2, "9OMY1": 2, "9ONDD": 2, "9PAQ4": 1, "9PXC0": 3, "9PXI9": 2, "9RA4P": 1, "9REZ6": 1, "9RRED": 2, "9RSGO": 1, "9RVZL": 2, "9RZ97": 5, "9SNMR": 1, "9SP9P": 3, "9T0AC": 1, "9T11N": 4, "9TL3J": 1, "9TPP3": 1, "9UDMH": 5, "9UNLE": 1, "9UTFJ": 1, "9UU4W": 6, "9V66G": 3, "9VBJ5": 1, "9VF2C": 2, "9VK0J": 1, "9VZOY": 3, "9W681": 1, "9X208": 1, "9XFJX": 1, "9XXJ7": 2, "9YI82": 1, "9YOI8": 3, "9YRHF": 2, "9Z1A3": 1, "9ZQ0R": 2, "A015X": 1, "A0CJL": 2, "A0CZE": 2, "A0T30": 2, "A0ZW3": 1, "A1NKP": 2, "A1PEO": 2, "A1VTR": 1, "A2EY4": 2, "A2X7Q": 2, "A2XH1": 3, "A2Z46": 3, "A33VQ": 1, "A3AV0": 1, "A3MOW": 4, "A3OWG": 1, "A3XXB": 2, "A3Y9O": 2, "A4SR3": 3, "A4VK8": 3, "A52N5": 2, "A54DW": 2, "A58GR": 2, "A58I2": 1, "A59CN": 3, "A5CRZ": 2, "A5XR5": 4, "A5YR8": 1, "A6CF6": 1, "A6NH2": 6, "A6UKL": 2, "A75XI": 3, "A7BUX": 4, "A7KHN": 1, "A7WU3": 1, "A81AV": 2, "A84J7": 1, "A8LZE": 1, "A8T8V": 2, "A96EQ": 1, "A9BDS": 3, "A9YQJ": 1, "AADCE": 2, "AAQHJ": 4, "AAS9S": 1, "AAW5D": 3, "AB06W": 3, "AB2V6": 3, "ABHC6": 2, "ABU7B": 1, "ACAK4": 4, "ACJBD": 1, "ACKR6": 1, "ACMHK": 2, "ACSP8": 3, "AD28I": 3, "AD9MO": 1, "ADK5J": 1, "AEJ4T": 3, "AEKYE": 4, "AEUVY": 1, "AEZDA": 2, "AF8IH": 1, "AFCDN": 2, "AFTMI": 2, "AFY37": 1, "AFY5E": 2, "AGELP": 1, "AGGSE": 2, "AGJH7": 2, "AGWQA": 1, "AGZ28": 1, "AH4UW": 1, "AHBE8": 3, "AHL6X": 2, "AI4NP": 2, "AI6KJ": 1, "AJ5YQ": 1, "AJLGU": 2, "AJTDO": 1, "AJZYE": 2, "AK2KG": 1, "AK9IB": 1, "AK9PN": 3, "AKU63": 1, "AL1WC": 2, "ALJ7B": 3, "ALXUC": 1, "AM3R2": 2, "AM4QC": 2, "AMIHY": 3, "AMLI4": 1, "AMT7R": 2, "ANA5N": 2, "ANAR5": 1, "ANXB8": 4, "ANZ0S": 1, "AO8RW": 1, "AOBWQ": 1, "AOK1L": 3, "AOQ7C": 1, "APH4V": 1, "APJQ8": 1, "APLZS": 4, "APQSV": 2, "APTS7": 1, "APVAD": 1, "APZUZ": 2, "AQ69X": 1, "AR7ZK": 1, "ARCUY": 2, "ARESU": 3, "ARKBT": 3, "ARWNX": 2, "AS7SG": 3, "AT9UV": 1, "ATCOR": 3, "ATI0Z": 1, "ATIAW": 1, "ATNBT": 1, "ATV2F": 3, "AUYOZ": 2, "AVJFE": 3, "AVL8A": 2, "AVSN8": 2, "AVSPS": 2, "AWAFY": 3, "AWCQN": 2, "AWGMW": 2, "AWITI": 2, "AWN1C": 1, "AWR2R": 2, "AWW55": 5, "AX46Z": 1, "AXFJP": 1, "AXJUB": 4, "AXKNF": 1, "AXS82": 1, "AYMCZ": 1, "AYSTI": 1, "AYXFY": 2, "AYZS4": 4, "AZ5JS": 1, "AZFKK": 1, "AZMVM": 2, "AZO8U": 1, "AZXRK": 4, "AZZ3W": 2, "AZZ7V": 2, "B0JWB": 2, "B0SV3": 2, "B0XI9": 3, "B17UQ": 1, "B1AMA": 3, "B1FY9": 1, "B2GXG": 1, "B32CU": 1, "B3HCE": 3, "B3SF6": 2, "B47TS": 1, "B4ED1": 5, "B4MNI": 3, "B5226": 2, "B53VP": 2, "B55HG": 1, "B57IW": 2, "B5R5B": 3, "B5VY1": 2, "B5X50": 1, "B69CF": 1, "B6LRC": 1, "B6S6T": 1, "B70WK": 1, "B71ZJ": 1, "B7DNX": 4, "B7LO8": 1, "B7SZJ": 2, "B82GJ": 1, "B8DL6": 1, "B8IYJ": 1, "B8JAF": 1, "B8PQL": 2, "B8W55": 3, "B9XZX": 2, "BAGJW": 1, "BAUQE": 1, "BB25Z": 1, "BB5DY": 2, "BB7WL": 1, "BB8Q0": 4, "BBAVF": 1, "BBQIS": 1, "BCONW": 2, "BCQWJ": 1, "BD0S7": 1, "BDJ84": 3, "BDWIX": 1, "BDY1V": 2, "BE43L": 5, "BE51K": 1, "BEAAA": 2, "BEC09": 1, "BEJVY": 2, "BEUCN": 2, "BFH78": 4, "BGQIF": 1, "BHXEI": 3, "BI31D": 1, "BI4PK": 1, "BI6Y4": 3, "BI86J": 2, "BID6Z": 3, "BIJYC": 2, "BIV8M": 2, "BIW43": 1, "BIZ2R": 2, "BJ7YW": 1, "BJI1D": 1, "BJXRT": 2, "BKEYX": 1, "BKNO9": 1, "BKXN4": 3, "BL7OF": 1, "BLB6G": 3, "BLFEV": 5, "BLIFO": 1, "BLIW5": 1, "BLPAB": 3, "BM3UJ": 3, "BM5B8": 1, "BM9NZ": 2, "BMLFA": 1, "BMONO": 3, "BMPEV": 1, "BMVXJ": 1, "BMYDX": 1, "BMYMI": 1, "BN4VH": 1, "BNEQL": 3, "BO62A": 1, "BOH8J": 2, "BOOKV": 1, "BOXK1": 2, "BPH56": 1, "BQA97": 1, "BQAUC": 1, "BQKW5": 2, "BQOLV": 2, "BQZ52": 1, "BR8B3": 3, "BRBWJ": 1, "BRE3P": 3, "BRLC0": 2, "BRLNM": 1, "BRQBD": 2, "BT1WN": 2, "BT8WU": 2, "BTN7H": 2, "BTR60": 2, "BUL4V": 2, "BUXV4": 2, "BVGMT": 2, "BVHA7": 2, "BVN7J": 4, "BW03C": 2, "BWG9B": 2, "BWKJB": 1, "BWLA8": 1, "BY6ZZ": 2, "BYP85": 1, "BYSQ7": 1, "BZ171": 2, "BZ1TH": 2, "BZ5N5": 2, "BZD0Q": 2, "BZMLV": 2, "BZWSJ": 1, "C1A2T": 1, "C1DK7": 3, "C1F1D": 3, "C1LJS": 1, "C1LVJ": 1, "C2QK3": 1, "C3HIN": 3, "C3JAS": 2, "C46TD": 1, "C4E9X": 1, "C4HHB": 1, "C4KZ4": 1, "C5BMA": 2, "C61BE": 1, "C69Y1": 2, "C6INR": 2, "C6LDA": 1, "C6LW1": 2, "C6V75": 2, "C7G1S": 1, "C7P86": 1, "C7R3J": 2, "C7V0X": 1, "C83CH": 1, "C8WLX": 1, "C93HZ": 2, "C9FMC": 2, "C9HLB": 1, "C9ISQ": 1, "C9VPX": 1, "CA5OI": 2, "CA7T0": 5, "CALKE": 2, "CB42N": 2, "CBG3N": 1, "CBLSW": 1, "CBPJF": 1, "CC610": 1, "CC6JC": 2, "CC87Z": 1, "CCCUJ": 3, "CCN3E": 1, "CCTIO": 1, "CD11G": 1, "CD9GP": 2, "CDIW7": 1, "CEL4V": 2, "CEM0H": 2, "CEPB8": 1, "CEQM1": 2, "CF1OQ": 3, "CF9QP": 2, "CFDXI": 2, "CFWP7": 1, "CG5KY": 2, "CG83G": 1, "CGNBJ": 3, "CH0PM": 2, "CH41S": 1, "CH8XJ": 1, "CI6H7": 2, "CII5H": 3, "CIL5L": 3, "CIUVA": 6, "CJ0U1": 2, "CJ58B": 3, "CJJ4Q": 1, "CJP4R": 1, "CK3H7": 1, "CK5SW": 1, "CKUYC": 2, "CLAWJ": 2, "CLORP": 3, "CLU7Z": 1, "CLW8L": 1, "CM0F0": 3, "CM293": 2, "CM5SK": 2, "CMC93": 3, "CMEA6": 1, "CMI7U": 2, "CN43X": 1, "CN5G4": 4, "CNSMI": 1, "COBEK": 1, "COBS0": 3, "COPHL": 3, "CPDJD": 4, "CPFLM": 1, "CPH1Y": 1, "CPM4M": 3, "CR1OK": 2, "CR5G1": 2, "CRH69": 2, "CRTUY": 3, "CS7HY": 2, "CS8O0": 1, "CSHUE": 2, "CSLEP": 2, "CSPSU": 3, "CSYES": 2, "CTCO8": 3, "CUD1T": 2, "CUHT0": 1, "CUQYX": 3, "CV20O": 2, "CV5YJ": 2, "CVDZM": 2, "CVK5Z": 3, "CVPQR": 2, "CVTII": 1, "CVX3K": 3, "CWBHH": 1, "CWM1T": 1, "CWMSY": 2, "CWUDQ": 1, "CX5ZM": 1, "CXF35": 1, "CXGSD": 2, "CXNYW": 2, "CXO6P": 1, "CXSYS": 1, "CY6U7": 3, "CYT5I": 2, "CZPFO": 2, "CZY4Q": 3, "D07V2": 2, "D09K3": 1, "D0AGO": 2, "D0E8H": 6, "D0V0Y": 1, "D0YWV": 1, "D1D55": 2, "D1NT7": 2, "D1UWI": 1, "D1VWG": 2, "D1WYU": 2, "D1XNV": 1, "D24XF": 1, "D2CEL": 1, "D2ES2": 1, "D2T7Z": 2, "D2VU8": 3, "D32A4": 2, "D3EY0": 1, "D3KN2": 1, "D3N3P": 1, "D4D2T": 4, "D4LRR": 1, "D52S5": 2, "D548M": 1, "D5886": 3, "D5IDA": 3, "D67MQ": 1, "D69VI": 1, "D6D85": 2, "D6MZ4": 2, "D740L": 2, "D7KU2": 1, "D7LMI": 2, "D7M6N": 2, "D7MHV": 1, "D85MK": 2, "D87LI": 3, "D8K7T": 1, "D8OSC": 1, "D98TV": 1, "D9EDE": 1, "D9F5V": 2, "D9FR4": 1, "D9YWY": 2, "DA7E9": 2, "DAA3F": 4, "DACFC": 4, "DB52Q": 2, "DBN7R": 2, "DBT6E": 2, "DC94A": 2, "DCFYV": 2, "DD3Q1": 2, "DDUXF": 2, "DDV1G": 1, "DDWK5": 1, "DECCY": 2, "DED50": 5, "DEJ35": 3, "DEQ73": 1, "DEXMO": 1, "DEZJ5": 2, "DFEG2": 2, "DFG9M": 1, "DFJ3N": 2, "DFPOJ": 2, "DG33V": 1, "DGHSW": 1, "DGMDT": 2, "DGPAW": 1, "DH66I": 2, "DHFA6": 2, "DHPNN": 2, "DHR5F": 1, "DHR83": 3, "DICXG": 2, "DIM24": 2, "DINAV": 2, "DINJ4": 1, "DIR8Q": 2, "DJJ24": 1, "DJMZC": 1, "DJVZQ": 3, "DKTVI": 2, "DLBRW": 1, "DLKWO": 1, "DLQIT": 3, "DMANO": 1, "DMI87": 2, "DMO76": 1, "DNWCR": 2, "DO48Z": 2, "DOB0W": 1, "DOGYU": 2, "DOL47": 1, "DOYQE": 2, "DP5S8": 1, "DP7DG": 2, "DPB7X": 2, "DPBI3": 1, "DPCGS": 2, "DPLMM": 1, "DQ1TU": 3, "DQ46N": 2, "DQEC3": 3, "DQGYG": 3, "DR4R7": 1, "DR7K0": 1, "DRGKV": 1, "DRIWX": 1, "DRXNL": 3, "DSG0F": 2, "DSGVL": 3, "DSI0N": 3, "DSZYT": 2, "DTJ6B": 3, "DTJS6": 2, "DTUJD": 1, "DU7H1": 3, "DUHWU": 1, "DUZDL": 2, "DV6CH": 2, "DVBVZ": 3, "DVDU2": 3, "DVHIB": 2, "DVM8I": 2, "DVO31": 3, "DVPL2": 1, "DWEHS": 2, "DWH0T": 2, "DWHPO": 3, "DWU60": 3, "DXUQS": 1, "DY9AE": 3, "DYGB7": 2, "DZ0SB": 4, "E002I": 2, "E06A2": 1, "E0AEN": 3, "E0IME": 4, "E0MK4": 3, "E0U3R": 2, "E0ZBC": 5, "E18UD": 3, "E1TJI": 1, "E1VFZ": 1, "E27NK": 5, "E2EHR": 2, "E2Q68": 3, "E33IO": 1, "E3S4O": 1, "E40Y8": 3, "E5TW6": 5, "E5ZF5": 3, "E6389": 2, "E653K": 1, "E6A0Y": 1, "E6PSM": 2, "E6RD3": 2, "E6TED": 1, "E780X": 2, "E7FGK": 3, "E7GV1": 1, "E7Q3R": 2, "E8468": 1, "E84XY": 2, "E891N": 1, "E89S9": 2, "E8C24": 1, "E9EKR": 1, "E9FY2": 3, "E9UYZ": 3, "EAKL5": 1, "EASCD": 5, "EAWW4": 1, "EBCTL": 1, "EBHC9": 1, "EBTD6": 2, "EC695": 2, "ECCW2": 3, "ECLIB": 3, "ECMQU": 2, "ECW3E": 1, "ECXEX": 2, "ED6VQ": 2, "EDBSA": 1, "EDPTO": 2, "EDVAM": 1, "EDXBD": 1, "EE8OB": 2, "EEGGA": 4, "EEVD3": 3, "EF2YJ": 1, "EFADI": 2, "EFD6M": 2, "EFIA2": 2, "EFR6I": 2, "EFUTW": 2, "EG0VZ": 3, "EG1XK": 1, "EGNZB": 1, "EGVGL": 1, "EGY7O": 2, "EHHRS": 1, "EHIOY": 3, "EHT0A": 1, "EI5M3": 2, "EIB97": 2, "EIKUN": 2, "EIT66": 1, "EJIKG": 1, "EJL2F": 2, "EJPO8": 3, "EJZZZ": 2, "EK19H": 2, "EK5K1": 3, "EL3N9": 2, "ELBLK": 2, "ELRP9": 3, "EM0B6": 3, "EMF9Q": 1, "EMWAP": 1, "EMXAG": 1, "EMYSA": 1, "EN0CD": 1, "ENCXV": 1, "ENJ7V": 1, "ENOLD": 1, "EO3G8": 2, "EO6OI": 4, "EOAR1": 1, "EOD1J": 1, "EOELV": 1, "EOUCM": 1, "EQ4GN": 3, "EQO9N": 2, "EQQ2T": 1, "ES10S": 2, "ESM8H": 1, "ET224": 5, "ET9EE": 1, "ETS92": 1, "ETT15": 2, "ETY8D": 1, "EU10X": 3, "EUJK0": 2, "EURF2": 2, "EVU9O": 2, "EW3VV": 1, "EW8GX": 2, "EWBOG": 2, "EWCV4": 1, "EWES1": 3, "EWH3D": 2, "EX1PY": 2, "EXG45": 2, "EXPOA": 2, "EXYY8": 1, "EY6P4": 1, "EYV38": 1, "EYZXC": 2, "EZCPC": 2, "F024X": 1, "F08QY": 1, "F0ZPW": 5, "F19VE": 3, "F1C8I": 1, "F1DQD": 2, "F1FV0": 2, "F1GWF": 1, "F1OMV": 2, "F1QR1": 2, "F1V30": 1, "F1VEE": 3, "F207R": 2, "F24GU": 1, "F2EA8": 2, "F2KKH": 1, "F2NAW": 1, "F3A3T": 4, "F3M1Q": 1, "F3O37": 1, "F3RM9": 2, "F3ULU": 1, "F44A2": 4, "F4BJJ": 2, "F4TXY": 2, "F5C5M": 4, "F5OZ5": 1, "F5TL0": 1, "F5UVQ": 1, "F64IO": 1, "F6A4W": 1, "F6Z7U": 1, "F7OOB": 1, "F7TG5": 1, "F87KZ": 1, "F8E8C": 3, "F8HLI": 1, "F8M2Y": 2, "F8PNY": 1, "F8TWE": 1, "F8UU2": 3, "F99PM": 2, "F9K8L": 1, "F9YMU": 2, "FAJEA": 3, "FAO7J": 3, "FAZXS": 1, "FB3ZG": 1, "FB7MZ": 2, "FBIVN": 1, "FBOF0": 1, "FC2SK": 5, "FCBEQ": 1, "FCDXN": 1, "FD9A5": 1, "FDDDG": 2, "FDIJX": 1, "FDPHZ": 1, "FDVBR": 1, "FETME": 1, "FFBK3": 2, "FFYL6": 1, "FGRL2": 5, "FGY8R": 3, "FH9AB": 1, "FHAV0": 2, "FI2DL": 1, "FI2TP": 2, "FIA2R": 1, "FIAJP": 1, "FIJ3D": 2, "FJIMX": 1, "FJRGJ": 1, "FJXBX": 1, "FJYZH": 1, "FK143": 2, "FKAGD": 3, "FKGY7": 1, "FKJ9L": 1, "FL4NG": 1, "FL6DF": 2, "FLDHS": 3, "FLM1T": 2, "FM078": 4, "FM3TT": 1, "FM5D5": 2, "FM6KD": 2, "FMJZQ": 1, "FMXZS": 2, "FMZOY": 2, "FN0F8": 1, "FNM0L": 3, "FNNTW": 2, "FNPEY": 1, "FNPOB": 1, "FO24A": 1, "FO9B1": 1, "FOMJM": 1, "FORXE": 2, "FP5MM": 2, "FP7N3": 2, "FPJKR": 1, "FPODN": 2, "FPQRX": 2, "FPU57": 1, "FPWD0": 2, "FQ282": 2, "FQ6OB": 3, "FQ9QX": 1, "FQA3W": 2, "FQAAB": 1, "FQGQS": 1, "FQGW4": 2, "FQIM2": 1, "FQM2N": 1, "FQOGZ": 3, "FQS5V": 2, "FQS7O": 4, "FR063": 1, "FRC6O": 2, "FRGXE": 1, "FRLW2": 1, "FRSBQ": 2, "FSKKQ": 1, "FSWT4": 2, "FT3D7": 1, "FTETB": 1, "FTG07": 5, "FTWBB": 3, "FU5NY": 1, "FU7HP": 2, "FUT86": 4, "FV51S": 2, "FV9AL": 1, "FVDNY": 1, "FVINY": 6, "FVITB": 2, "FVMVY": 1, "FVSB0": 1, "FWUV8": 2, "FX1T5": 1, "FX7ZY": 2, "FXC28": 1, "FXIVQ": 3, "FXRMG": 2, "FYJHS": 3, "FYJJT": 1, "FYR3P": 1, "FYU0D": 1, "FYYFX": 2, "FZ0LU": 1, "FZ6AD": 1, "FZAEP": 1, "FZBK6": 1, "FZIW9": 2, "FZJTT": 3, "G0BKH": 2, "G1CM7": 3, "G1NFB": 3, "G24CA": 2, "G2AMK": 3, "G2DIN": 1, "G2QBV": 2, "G3K6P": 2, "G3WBE": 4, "G41CL": 2, "G4AJK": 4, "G4E4S": 2, "G4JHX": 1, "G4KE3": 1, "G4MDY": 2, "G4MNO": 2, "G4NOT": 1, "G4VTC": 4, "G4WCE": 2, "G537E": 2, "G54NU": 2, "G5G8K": 2, "G6LYD": 1, "G6MYM": 3, "G6ZOB": 2, "G71O7": 3, "G71VM": 1, "G7K5A": 2, "G81JB": 2, "G87XG": 2, "G8NEV": 4, "G8O8P": 1, "G8SWD": 1, "G8V6N": 1, "G8YWY": 1, "G9I7C": 1, "G9IUG": 2, "GA4EI": 1, "GA7SB": 2, "GANC6": 1, "GBD1Y": 3, "GBDJX": 2, "GBMNT": 2, "GBZAK": 3, "GC1Q1": 2, "GC7L9": 1, "GC9I8": 1, "GCI2J": 2, "GCWNT": 1, "GD1LA": 1, "GDIW0": 1, "GDS6Q": 1, "GDTYU": 3, "GE4SD": 2, "GEAB1": 2, "GEJPM": 4, "GF6TR": 1, "GFK4S": 2, "GFPDD": 1, "GFVSV": 4, "GG1X2": 2, "GG3K5": 1, "GG4UR": 2, "GGAN0": 1, "GH19N": 2, "GH3D1": 1, "GHJ3Q": 2, "GHJ8Z": 1, "GHJCC": 1, "GIIF8": 2, "GIZ95": 1, "GJC0W": 2, "GJNI4": 1, "GK08Z": 2, "GK15U": 1, "GK7S7": 1, "GKBSR": 1, "GKH0F": 4, "GKH4A": 2, "GL7E6": 3, "GL7ER": 3, "GLGQJ": 3, "GLIC0": 2, "GLLNH": 2, "GLSU2": 3, "GM3UK": 2, "GM4QR": 1, "GM4UP": 1, "GMLPK": 3, "GMMVC": 2, "GMPHO": 5, "GMSTS": 1, "GN0M8": 1, "GN4SJ": 2, "GN912": 1, "GNUZK": 1, "GO761": 1, "GOCDE": 2, "GOPZI": 2, "GOWDG": 1, "GP5CT": 1, "GPJ6E": 1, "GPR89": 3, "GPSIM": 3, "GQ341": 3, "GQ4ML": 2, "GQGAE": 3, "GQKIU": 1, "GQR08": 1, "GR4MX": 1, "GR5N6": 2, "GRBUE": 1, "GRJG1": 1, "GSIYV": 2, "GT07A": 3, "GTK8W": 3, "GV0L7": 3, "GV9M4": 2, "GVHM9": 1, "GW2Y8": 4, "GWDF9": 2, "GWK2L": 1, "GWUM6": 1, "GWZMQ": 2, "GXDGV": 1, "GXIWH": 1, "GXVX8": 1, "GXZHG": 2, "GY8P2": 1, "GYAR9": 5, "GYRQH": 2, "GYVK9": 1, "GZF5F": 2, "GZQ0V": 1, "GZSTG": 2, "H032R": 2, "H047B": 2, "H0L5S": 1, "H0Q6V": 3, "H1GWM": 1, "H1XBH": 3, "H2B7U": 1, "H32FR": 1, "H378S": 1, "H3CDC": 1, "H3XC1": 1, "H40VV": 1, "H411A": 3, "H41MY": 1, "H4ZD8": 2, "H51V5": 2, "H5CJD": 1, "H5TGJ": 1, "H5ZG9": 2, "H603E": 6, "H608V": 2, "H6ROK": 1, "H76DJ": 1, "H7LQM": 2, "H8BTR": 3, "H8S4L": 1, "H8UJ3": 4, "H9U38": 2, "H9V9I": 1, "HA02S": 1, "HA8MN": 1, "HAPCT": 2, "HB4AB": 1, "HB8QW": 1, "HB9LP": 1, "HBPZJ": 2, "HBWLV": 3, "HC5JH": 2, "HC62A": 2, "HCM5Y": 1, "HCSPE": 1, "HD38O": 5, "HD6GF": 1, "HDDU0": 2, "HDMN4": 2, "HEOJM": 1, "HFTEO": 2, "HFW6H": 3, "HFWE9": 1, "HGSB7": 1, "HGZ0V": 2, "HH1R7": 2, "HHAM7": 1, "HHCFO": 3, "HHEIV": 1, "HHNTA": 1, "HHZUI": 2, "HI4NV": 3, "HI81L": 3, "HIOY0": 2, "HITEM": 1, "HJ4B1": 3, "HJ8U7": 1, "HJH7H": 1, "HJJ32": 2, "HJM82": 1, "HKJUR": 1, "HKLB1": 1, "HKS9J": 1, "HKSI2": 1, "HKY1M": 1, "HL5OP": 2, "HLB3J": 4, "HLMQ8": 1, "HLUMT": 1, "HMA8E": 1, "HMLJX": 3, "HN362": 3, "HNPC8": 1, "HNPX7": 2, "HNTS9": 1, "HOGVD": 1, "HOI6L": 2, "HOI88": 2, "HONL7": 2, "HONRP": 1, "HOYUT": 2, "HOZ76": 2, "HPAYB": 1, "HPEE5": 2, "HPFF1": 1, "HQ8K2": 1, "HQ8ZM": 1, "HQUHP": 2, "HQZ29": 1, "HR6MF": 2, "HRASP": 3, "HRR0X": 2, "HS14N": 2, "HSH5R": 1, "HSKVH": 2, "HSWPR": 3, "HT9YB": 2, "HTCKH": 1, "HU409": 1, "HURN7": 1, "HVFXT": 2, "HVUH9": 1, "HVZUQ": 1, "HWHLG": 1, "HWLBL": 3, "HXCGX": 2, "HXQ55": 1, "HXR3Z": 3, "HXSMP": 1, "HXUI5": 2, "HYD3N": 2, "HYEY7": 2, "HYOQB": 1, "HYR9Q": 2, "HYRBL": 3, "HZSDD": 1, "HZTB1": 4, "HZXXN": 1, "I005F": 1, "I164P": 1, "I1OLQ": 2, "I20II": 1, "I20N2": 2, "I2DHG": 2, "I329H": 2, "I3N3J": 2, "I4K7B": 2, "I4N6K": 3, "I4OFW": 1, "I4ON2": 1, "I52A6": 2, "I562C": 4, "I5F23": 3, "I5L3Y": 2, "I5LAC": 2, "I5U4Q": 1, "I5ZWF": 2, "I68J0": 2, "I6H4R": 1, "I6KKY": 1, "I6NJ6": 1, "I713Z": 2, "I75CL": 4, "I79Q6": 2, "I7AS7": 2, "I7DGO": 2, "I7MEA": 2, "I80TD": 2, "I87SH": 1, "I8BC5": 1, "I8I5F": 1, "I8LEO": 1, "I9SSV": 2, "IA7X9": 1, "IACBH": 1, "IAHN3": 1, "IAK2E": 2, "IBIWF": 1, "IBNKL": 3, "IBRFM": 1, "IBX56": 2, "ICL1M": 2, "ICOX1": 2, "ICQUJ": 3, "ICQZX": 2, "ICXAE": 2, "IDXZK": 2, "IEQWT": 1, "IET7H": 2, "IEZFM": 2, "IFFPZ": 1, "IFO3G": 1, "IFQS1": 1, "IFRT0": 2, "IG1YT": 2, "IGEU5": 1, "IGF81": 1, "IGVLE": 1, "IGZZG": 1, "IHSRC": 1, "III9I": 1, "IIJ5I": 1, "IIL9C": 4, "IIW0F": 2, "IJ01G": 2, "IJ3QB": 2, "IJNBL": 1, "IJOAK": 3, "IJZ4F": 1, "IK4Q8": 2, "IK72J": 1, "IK8PA": 2, "IKJB4": 1, "IKYVB": 1, "IKZJE": 2, "IKZN3": 2, "IL0JH": 1, "IL0LY": 1, "ILKXV": 2, "IM2WK": 1, "IM3I0": 2, "IN2RL": 3, "INA5N": 2, "ING5Z": 3, "INKPE": 1, "INQNU": 1, "IO712": 3, "IOBKP": 3, "IOGR7": 2, "IOMVF": 1, "IONV9": 2, "IP2EA": 5, "IPH08": 1, "IQ0ZX": 3, "IQA16": 2, "IQSWM": 1, "IR31O": 1, "IS3OX": 1, "IS7PL": 2, "IST7I": 2, "ISTQI": 2, "ITDHX": 1, "ITJIY": 2, "ITJZB": 1, "ITODQ": 2, "ITXRK": 2, "IU5TH": 2, "IUBYO": 1, "IUGG8": 1, "IULK6": 2, "IULMX": 1, "IUOC0": 2, "IV1S7": 2, "IV1U5": 1, "IV7IZ": 1, "IVJWH": 1, "IWF0U": 3, "IWK2Y": 1, "IWTWJ": 1, "IX64X": 3, "IXISD": 2, "IXJKT": 1, "IXVGR": 2, "IXY95": 2, "IYD9U": 1, "IYU90": 2, "IZ2XX": 1, "IZCB0": 1, "IZSPN": 2, "IZZ3Y": 1, "J06RS": 1, "J0AMJ": 4, "J0SZG": 1, "J1RLO": 1, "J2DBI": 2, "J2XFQ": 1, "J3LZI": 1, "J3RD3": 2, "J3RP9": 1, "J3UKN": 3, "J3ZQS": 4, "J3ZZH": 1, "J4GX8": 1, "J4QHT": 2, "J4RPL": 2, "J4U86": 1, "J53NS": 1, "J5CAN": 1, "J5DOP": 3, "J5K87": 7, "J647I": 2, "J6L8A": 3, "J6P6H": 1, "J6TVB": 3, "J6WE2": 2, "J76NX": 2, "J7BOV": 2, "J84TZ": 1, "J867Z": 1, "J8781": 2, "J8JOQ": 2, "J8KPE": 1, "J95X1": 2, "J9T5D": 3, "JAOPD": 1, "JBHOL": 1, "JBJGX": 2, "JBY4E": 3, "JBZF5": 2, "JC1DV": 1, "JC9SA": 2, "JCGWC": 1, "JCKRL": 1, "JCNHL": 1, "JCUT2": 1, "JCWVV": 3, "JD3KW": 2, "JDDD8": 2, "JEB7V": 6, "JEDTE": 3, "JELL2": 2, "JF36Q": 1, "JFBTV": 3, "JFR2I": 3, "JFSJF": 2, "JFU3J": 1, "JFXG8": 1, "JG7UX": 2, "JGYF6": 2, "JHB0M": 2, "JI3ZF": 3, "JI705": 2, "JIGAJ": 1, "JIR5V": 2, "JIS2Q": 1, "JISS4": 1, "JJ47B": 2, "JJ7M6": 1, "JJLTF": 1, "JJON5": 2, "JKGTN": 3, "JKR9A": 1, "JKWJ6": 3, "JKZG5": 1, "JKZUM": 1, "JL1W2": 1, "JL3VT": 1, "JL5O0": 2, "JL6MG": 4, "JL8XT": 3, "JLGLU": 1, "JMA1R": 1, "JMCRT": 2, "JMTI2": 2, "JMXK5": 2, "JN2E8": 1, "JNWX7": 2, "JO6GB": 2, "JOLLV": 3, "JOMFO": 2, "JOWAU": 1, "JOYAJ": 1, "JP5NM": 2, "JP60G": 1, "JPEM7": 2, "JPEQK": 1, "JPUUF": 1, "JPVSV": 1, "JQ2SN": 3, "JQHIC": 1, "JQKR5": 4, "JQLD3": 2, "JQW5G": 1, "JQY4L": 1, "JSD0F": 1, "JSLW5": 1, "JSY2I": 2, "JT537": 1, "JTBXI": 2, "JTM7L": 1, "JTXAM": 1, "JTXUA": 2, "JTZZW": 2, "JUF24": 1, "JUI9U": 1, "JV524": 1, "JVISI": 4, "JVOM3": 2, "JVXMI": 1, "JW2HC": 2, "JWPS5": 3, "JX18W": 1, "JX8SN": 1, "JXNEN": 3, "JXS3A": 2, "JXTAD": 1, "JY6TC": 1, "JZ45I": 5, "JZ46A": 1, "JZB97": 3, "JZDL6": 1, "JZULS": 1, "K0C0A": 2, "K0FAG": 3, "K0IGF": 1, "K0X80": 1, "K0Y6X": 2, "K0Z9V": 1, "K14NJ": 2, "K1D2G": 1, "K1M15": 1, "K2LY1": 1, "K3193": 1, "K34BE": 2, "K47J5": 2, "K48CQ": 4, "K4UOG": 2, "K4X20": 1, "K4XO7": 1, "K56PA": 1, "K5CRM": 2, "K5IAK": 3, "K5NFS": 1, "K63HG": 1, "K6DF2": 2, "K6KNC": 1, "K6W5I": 3, "K71S1": 2, "K7E8L": 1, "K7NRW": 2, "K7VCU": 2, "K7X5G": 2, "K7Z6T": 1, "K87AC": 2, "K8H4G": 1, "K8OB6": 3, "K8ZIK": 2, "K90LN": 2, "K9EAZ": 1, "K9HPB": 1, "K9MPN": 1, "K9RH2": 3, "K9UXS": 2, "K9V2R": 1, "KA09C": 2, "KAFV7": 1, "KAKC6": 4, "KAQNT": 1, "KB916": 2, "KC863": 1, "KCLMY": 1, "KCRQU": 2, "KD2H4": 1, "KDK62": 1, "KE5EM": 2, "KENG1": 2, "KEPDQ": 1, "KERO6": 1, "KEY1O": 1, "KFC28": 1, "KFD4I": 1, "KFGEF": 2, "KFGXC": 1, "KFHLP": 2, "KFI7N": 1, "KFM5Q": 3, "KFZ55": 2, "KG2LF": 1, "KGMA5": 1, "KGO3W": 2, "KHWG2": 2, "KHWI5": 2, "KHXGJ": 1, "KI0Q7": 1, "KI6RS": 1, "KIJG4": 1, "KJ428": 1, "KJ8G2": 1, "KJK56": 3, "KK7D4": 2, "KK8N9": 1, "KKGJ8": 1, "KKGLB": 2, "KKONU": 5, "KKP3R": 1, "KLO0K": 1, "KLP7V": 1, "KMAQ2": 2, "KN0TK": 1, "KNDY2": 2, "KNGRY": 4, "KNGUT": 2, "KNIZK": 1, "KNN3G": 4, "KNX2Y": 2, "KO2MY": 3, "KO34N": 1, "KO80I": 2, "KOHWO": 1, "KONWE": 2, "KOQGE": 2, "KOVTR": 3, "KP53W": 1, "KP88I": 1, "KPAS0": 1, "KQ6XW": 3, "KQDX6": 2, "KQLIJ": 1, "KQNOV": 2, "KQYR0": 2, "KR0SH": 3, "KRF68": 2, "KRLT7": 1, "KRRBE": 1, "KS0FF": 2, "KSAU8": 1, "KSIYE": 1, "KSPZY": 2, "KT3MJ": 1, "KTDG0": 1, "KTKWL": 1, "KTL2G": 1, "KTOJX": 2, "KTXE0": 1, "KU656": 2, "KUBUA": 1, "KUO3N": 2, "KV99H": 2, "KVYOZ": 1, "KW3BO": 2, "KW4Y1": 1, "KWONB": 2, "KWQKH": 3, "KWZSA": 3, "KX7FC": 1, "KX8VW": 3, "KX90W": 1, "KXAIZ": 3, "KXCSL": 1, "KXIMH": 2, "KY2KA": 3, "KZ746": 2, "KZ7Y8": 1, "KZN8C": 2, "KZODG": 2, "KZR42": 4, "KZS5M": 3, "KZSA9": 2, "L071S": 2, "L09BS": 1, "L0HDB": 3, "L0NFK": 1, "L0QNM": 1, "L0YQM": 2, "L1BNN": 2, "L1MR4": 1, "L1S6P": 2, "L218P": 1, "L29HE": 1, "L2LF6": 1, "L2ZZB": 2, "L347E": 1, "L36YT": 1, "L4DUU": 2, "L4VNK": 1, "L57L2": 2, "L5842": 1, "L58KN": 1, "L5TI4": 2, "L5YHH": 3, "L5ZAB": 1, "L62J5": 1, "L76ND": 2, "L7HA6": 2, "L8HMR": 2, "L8T4O": 1, "L8WFE": 1, "L8Y8D": 3, "L9ANI": 3, "L9H3O": 2, "L9J5I": 2, "LA0DB": 1, "LB4AR": 2, "LBG7L": 3, "LBGFT": 1, "LBRYS": 1, "LC1NU": 3, "LCEM0": 5, "LCLLN": 4, "LCZ8F": 2, "LD011": 1, "LD6TD": 4, "LD8PU": 1, "LDNE2": 1, "LE7PM": 1, "LEG82": 5, "LF49A": 1, "LFBCQ": 1, "LFPLP": 1, "LFU36": 2, "LG73V": 1, "LG7WK": 1, "LGCTV": 2, "LGPWK": 1, "LGS4C": 1, "LH6LE": 3, "LHMMJ": 1, "LHTSI": 2, "LI5VF": 1, "LIXE6": 2, "LJ2J6": 1, "LJ3AI": 2, "LK3BW": 1, "LK3LF": 3, "LKH9A": 4, "LKNZD": 4, "LKSBL": 2, "LKYCT": 2, "LLE9B": 4, "LLOGB": 2, "LLQBB": 1, "LLRKS": 2, "LNEAG": 1, "LNWWJ": 1, "LOBSL": 2, "LOH86": 2, "LOP4H": 2, "LOSLI": 1, "LP1F3": 2, "LP47Z": 1, "LPJWM": 1, "LPT4A": 1, "LQ0FJ": 2, "LQC89": 3, "LQD66": 1, "LQEB5": 1, "LQGMM": 3, "LQO5R": 1, "LR0L8": 3, "LRDW5": 2, "LRJKT": 3, "LRJS4": 1, "LRQXG": 2, "LSCMZ": 1, "LSKA2": 1, "LSVHK": 1, "LSY08": 1, "LT13Z": 3, "LT2IJ": 3, "LTC5Y": 3, "LTYK5": 1, "LU3SU": 2, "LU82W": 1, "LUQWY": 4, "LURLC": 2, "LUYWY": 3, "LV760": 1, "LVGX3": 2, "LVTRJ": 3, "LW1W2": 2, "LW51F": 2, "LW5O6": 1, "LWB5E": 1, "LWEPB": 2, "LWINQ": 2, "LWJGN": 1, "LWRKS": 1, "LXEPT": 4, "LXJ86": 1, "LY10X": 1, "LYDEA": 1, "LYO14": 1, "LYXGZ": 1, "LYY21": 2, "LZ2Y4": 2, "LZTH6": 1, "M014B": 3, "M0KKW": 1, "M0KTN": 2, "M149H": 2, "M18XP": 2, "M1B7N": 2, "M1FNW": 2, "M1GW9": 2, "M1SRW": 1, "M1TZR": 3, "M2DD1": 2, "M2F66": 2, "M2XIS": 2, "M3EAQ": 1, "M3H7V": 1, "M3OMM": 1, "M3S4D": 1, "M40WF": 2, "M43KR": 3, "M4D35": 1, "M4FOP": 1, "M4FW0": 2, "M4Z0M": 1, "M506V": 3, "M52K2": 2, "M5S4U": 1, "M5UQR": 2, "M5W51": 2, "M6ERH": 1, "M6HAF": 1, "M6LFI": 1, "M704T": 2, "M7BD4": 2, "M7DIB": 1, "M7Y6V": 4, "M8NZA": 2, "M8OYC": 3, "M8PXK": 4, "M98YV": 2, "M9KMN": 2, "MA15X": 7, "MA1ON": 1, "MAMJ8": 1, "MAPVV": 1, "MBAA5": 3, "MBYRJ": 1, "MC50M": 1, "MC6J7": 2, "MCMTH": 1, "MCNRZ": 2, "MD6P2": 3, "MDG2T": 4, "MDXF4": 2, "ME7II": 1, "MERBU": 1, "MEYZ5": 2, "MF09L": 5, "MF8AX": 1, "MFQ5S": 1, "MGDO2": 1, "MH601": 1, "MHAGN": 2, "MHI9B": 3, "MHTRY": 1, "MI0UK": 1, "MI76A": 1, "MIAE4": 1, "MILRI": 1, "MIRSU": 1, "MIV2M": 2, "MJYTA": 2, "MKDCU": 2, "MKMFK": 1, "MLBTH": 4, "MLHCK": 2, "MLK57": 2, "MLKK5": 1, "MLS4T": 1, "MMFQA": 2, "MMGTX": 1, "MMKKS": 1, "MMRRV": 1, "MN1MC": 3, "MNC10": 1, "MNEQ4": 1, "MNNDB": 2, "MNNJS": 2, "MO0SA": 3, "MOA3N": 1, "MOQIU": 3, "MOREL": 3, "MOT57": 1, "MOTWW": 2, "MP6JQ": 2, "MPBRL": 3, "MQ4YR": 1, "MQ9PZ": 3, "MQGVS": 2, "MQXAJ": 1, "MR66M": 2, "MRNFI": 1, "MRSYL": 1, "MRZ44": 1, "MS58Y": 1, "MSN1B": 1, "MSQA1": 2, "MSW4E": 1, "MT6C2": 1, "MTA02": 1, "MTLT3": 1, "MU6UQ": 2, "MUE7H": 1, "MUGVM": 2, "MUI01": 1, "MUO4G": 1, "MUQBW": 5, "MUZMD": 2, "MV0TX": 4, "MV37M": 1, "MV9N4": 2, "MVPPS": 2, "MVPQF": 2, "MVX03": 2, "MWAGL": 2, "MWX5K": 1, "MWZJY": 1, "MX4FM": 1, "MX9XB": 2, "MXATD": 1, "MY5CQ": 2, "MY7NU": 2, "MY9UC": 1, "MYBRN": 2, "MYPU6": 2, "MYQZJ": 3, "MYZLT": 1, "MZ3I3": 3, "MZ3X9": 2, "MZGMN": 2, "MZHDX": 3, "MZJ9D": 1, "MZK2X": 1, "MZZ8Q": 1, "N0G70": 2, "N0KQ7": 2, "N0N4I": 2, "N0ZPI": 2, "N14BK": 2, "N1DAP": 1, "N1EDG": 1, "N1RJW": 1, "N2DZN": 1, "N2GFQ": 2, "N2TPE": 1, "N2WXN": 2, "N2XCF": 4, "N3OKQ": 4, "N3SBJ": 5, "N50C6": 1, "N513D": 4, "N56QO": 1, "N5895": 1, "N59H5": 1, "N5PLR": 2, "N5Z8Z": 1, "N67PL": 3, "N6FZ7": 2, "N6R39": 3, "N7130": 2, "N7243": 2, "N79WJ": 2, "N7AOK": 1, "N7GBK": 1, "N7IH0": 3, "N7X3T": 1, "N7ZBM": 1, "N8R3F": 1, "N8WK8": 1, "N915C": 2, "N93LD": 2, "N93NK": 1, "N9TRF": 2, "NACLT": 1, "NAF1C": 2, "NALYS": 2, "NALYZ": 4, "NAZ52": 5, "NB6F5": 2, "NBAGZ": 2, "NBIR0": 2, "NBSPH": 4, "NC1OC": 5, "NCBNH": 2, "NCDE3": 3, "NCJ1X": 1, "NCRCW": 2, "NCZOV": 1, "NDBXV": 1, "NDLY5": 2, "NDX21": 4, "NDYOR": 2, "NE37I": 1, "NEE6E": 2, "NEM29": 3, "NF45F": 1, "NFA8R": 2, "NFXPI": 1, "NG1Q8": 4, "NGWRE": 3, "NGXV2": 2, "NGZQ9": 1, "NH3LX": 3, "NH9JS": 2, "NHD1J": 5, "NHH8N": 4, "NHSAW": 1, "NHUV1": 1, "NHXI3": 2, "NI15V": 2, "NIG0Z": 1, "NIH53": 1, "NIPVQ": 1, "NJANX": 2, "NJCDX": 4, "NKCXF": 2, "NKOJ8": 2, "NKTWF": 1, "NL0QB": 2, "NL7BY": 2, "NL9AW": 1, "NLM0B": 1, "NLU6W": 1, "NLWBW": 3, "NM65M": 1, "NMC3H": 1, "NMC5N": 1, "NMTRI": 2, "NNG97": 1, "NNUCA": 2, "NNZON": 1, "NO1GJ": 2, "NO9MI": 1, "NOFSE": 3, "NOJK1": 1, "NOLQ7": 1, "NPEA3": 2, "NPM0Z": 1, "NQKZB": 2, "NR94C": 2, "NR9L2": 1, "NSDFA": 1, "NSEZ8": 1, "NSF4N": 1, "NT2HT": 2, "NTXXB": 2, "NTYC3": 1, "NUKJ0": 1, "NUSKJ": 1, "NUW9G": 1, "NV4FC": 2, "NVBBD": 1, "NVF2S": 4, "NVGDG": 2, "NVKDC": 1, "NW0KT": 4, "NWFOF": 2, "NWGVT": 2, "NX5EW": 1, "NX8X9": 3, "NY0IW": 1, "NY5LX": 4, "NY5R2": 1, "NY8P3": 1, "NYHD7": 1, "NYPOF": 1, "NYXJ6": 3, "NYZL3": 2, "NZ7VY": 2, "NZCG8": 1, "NZG0R": 1, "O0349": 3, "O03Y4": 1, "O07KU": 1, "O18DS": 2, "O1D7K": 1, "O1J7D": 2, "O1LOW": 2, "O1NO0": 1, "O1YWR": 1, "O283L": 4, "O2DXE": 1, "O2OUX": 3, "O2VP8": 1, "O3HV7": 2, "O3Y57": 2, "O441U": 2, "O52BL": 2, "O6FSN": 2, "O6V4U": 1, "O76GM": 4, "O7FDB": 2, "O7KDK": 1, "O7N6K": 1, "O7NI6": 3, "O7OD2": 2, "O87OF": 3, "O8FBU": 1, "O8N4M": 2, "O8PO3": 1, "O8S0J": 3, "O8T6G": 2, "O9WFN": 1, "OA6XR": 1, "OA9W5": 2, "OAC4U": 2, "OADOE": 1, "OAHDH": 1, "OB1XO": 3, "OB660": 2, "OB7UK": 1, "OBTP8": 2, "OCSVQ": 1, "OCVY4": 2, "ODM20": 3, "OE2M1": 2, "OE2OX": 2, "OE751": 4, "OEE36": 1, "OEIRN": 6, "OELNE": 1, "OEM65": 5, "OETY6": 2, "OEUGC": 2, "OFCU3": 2, "OFFQ4": 2, "OFNQV": 2, "OGLCO": 3, "OHBYF": 2, "OHLSE": 4, "OHNF4": 3, "OHNUQ": 2, "OHQOO": 1, "OI3BC": 2, "OI7GQ": 1, "OIL1V": 1, "OINMN": 4, "OIRJ0": 1, "OIRPJ": 1, "OIXA4": 1, "OIZT9": 1, "OJ4IE": 2, "OJGGZ": 5, "OJIEC": 1, "OJIRT": 2, "OJLFZ": 2, "OJYDD": 3, "OK2AF": 2, "OKHVL": 5, "OKVGK": 2, "OKXIQ": 3, "OKYYQ": 2, "OL2QI": 1, "OLELC": 1, "OLSMC": 1, "OLV1L": 2, "OM2NF": 5, "OM5R4": 2, "OMBR9": 5, "OMFOJ": 1, "OMX6W": 1, "ON2VH": 1, "ON2Z4": 2, "ONA0S": 1, "ONMCW": 3, "ONT61": 1, "OO2SF": 1, "OO4FE": 3, "OOCOF": 1, "OOE32": 2, "OOEHL": 1, "OOWJ9": 3, "OP2SS": 2, "OPJG1": 1, "OPMF7": 1, "OPSF8": 3, "OQ54Y": 3, "OQ9W3": 4, "OQSXX": 3, "OR3G4": 1, "ORAT0": 2, "ORD96": 1, "ORJTD": 1, "ORPD5": 4, "ORUV6": 2, "ORW6Y": 2, "OSCS2": 2, "OSENM": 1, "OSIKP": 1, "OT35M": 1, "OTLX9": 4, "OTUV7": 2, "OU3HS": 3, "OU3XH": 4, "OUAIS": 2, "OUBUX": 3, "OUH2U": 1, "OVD84": 2, "OVFR0": 2, "OVFVJ": 3, "OVICR": 2, "OVMCM": 2, "OVYAC": 1, "OW9LO": 1, "OWAA9": 2, "OWGPH": 1, "OWLRQ": 2, "OWOCT": 2, "OWS57": 1, "OWUW8": 1, "OWXLM": 3, "OWZCZ": 1, "OX5TB": 1, "OXC4X": 1, "OXCDM": 1, "OXEMQ": 2, "OXKR5": 1, "OXUKR": 3, "OY3LS": 4, "OY50Q": 1, "OYG5H": 1, "OZ02A": 3, "OZ5SV": 2, "OZCGO": 1, "OZSB3": 3, "P0CET": 2, "P0ILN": 3, "P14L7": 2, "P1EK9": 2, "P1LWC": 1, "P2HZG": 2, "P2UBC": 2, "P36YW": 2, "P3EW1": 2, "P3XT7": 3, "P4DL9": 1, "P4FXX": 2, "P4HXN": 1, "P4KFQ": 1, "P4MBS": 3, "P4SB9": 1, "P5JRJ": 1, "P5SWU": 1, "P68QV": 2, "P6JGZ": 1, "P6SOI": 1, "P73KX": 1, "P73UC": 1, "P76D1": 2, "P7RQS": 1, "P87UK": 2, "P8G2P": 1, "P8G8V": 1, "P8UT3": 1, "P8ZU6": 2, "P981O": 1, "P9R08": 2, "PAA7V": 3, "PAW5E": 1, "PB0JI": 2, "PB7PQ": 2, "PBEUF": 2, "PC0M6": 1, "PCNUP": 1, "PDK24": 1, "PDRVY": 2, "PEIV4": 2, "PEKGD": 1, "PEY34": 1, "PFOD8": 1, "PFTHZ": 1, "PG1ID": 1, "PGGRZ": 1, "PGKB4": 1, "PH3R3": 1, "PH5VU": 3, "PHH49": 1, "PHH6B": 3, "PHIIX": 1, "PHN7Z": 1, "PHWKM": 1, "PIEHJ": 3, "PIJCA": 1, "PIJRH": 2, "PIRMO": 2, "PJDUN": 3, "PJO9R": 1, "PJUM0": 2, "PK2F0": 2, "PKEZI": 4, "PKNT2": 3, "PLGZM": 1, "PLJIZ": 3, "PM1VD": 4, "PM2GT": 1, "PM6U2": 2, "PM9HG": 2, "PMG3A": 5, "PN4MI": 4, "PN7CX": 3, "PNAXO": 3, "PNC99": 2, "PNVRJ": 1, "POACA": 1, "POLVK": 1, "PON7X": 2, "POXTH": 1, "PP2FF": 2, "PPKP0": 1, "PPXPA": 2, "PPY0W": 1, "PQX96": 1, "PQYWB": 2, "PRHR7": 1, "PRQSR": 1, "PRTAJ": 2, "PRV4N": 3, "PRVHF": 2, "PSCWP": 1, "PSPMA": 4, "PT0D1": 1, "PT4XS": 3, "PTA97": 1, "PTAZ9": 4, "PTPJL": 1, "PUA7P": 3, "PUWX2": 1, "PUY34": 1, "PUY9Q": 2, "PV745": 9, "PVAJ8": 3, "PVVQS": 1, "PW16K": 1, "PW3GG": 1, "PW9P0": 1, "PWJ3J": 1, "PWW6X": 1, "PXKFK": 1, "PXY5Q": 2, "PXYN8": 1, "PYIA3": 1, "PZ0MM": 2, "PZ0ND": 1, "PZ2W1": 1, "PZD7Z": 3, "PZNVV": 1, "PZQ5A": 1, "PZQIN": 1, "PZS0C": 2, "Q071E": 2, "Q07NE": 2, "Q0IHP": 1, "Q166J": 2, "Q18ZQ": 3, "Q1K00": 1, "Q1L24": 1, "Q1SV4": 1, "Q24GF": 2, "Q24KP": 1, "Q24OC": 2, "Q2U7O": 1, "Q366H": 2, "Q3BCC": 1, "Q3HZI": 2, "Q3M8J": 2, "Q3XBQ": 3, "Q4932": 3, "Q49E0": 3, "Q4TKG": 2, "Q4UO4": 2, "Q57HC": 1, "Q5MDU": 1, "Q5YDL": 5, "Q6M0X": 3, "Q6WH2": 1, "Q6ZD9": 1, "Q77UW": 3, "Q7DEB": 1, "Q7IQI": 3, "Q7RK6": 1, "Q7YXN": 1, "Q81A4": 1, "Q85TS": 1, "Q8QGT": 2, "Q8TB3": 1, "Q8UJ8": 2, "Q8XEE": 2, "Q948H": 5, "Q9DW7": 2, "Q9H04": 2, "Q9TIN": 1, "QACLT": 2, "QAHJG": 1, "QASDI": 1, "QBOOH": 2, "QBQR3": 1, "QBUAT": 3, "QC9M1": 1, "QCAUL": 2, "QCVZN": 2, "QD1U7": 3, "QDINO": 2, "QDOXA": 1, "QDRWK": 2, "QDVXO": 2, "QE4YE": 1, "QEFFJ": 2, "QEFJF": 2, "QEV60": 1, "QEXP4": 2, "QF1Y0": 3, "QFVMA": 3, "QG4N1": 1, "QGQGZ": 2, "QH3FK": 4, "QH3WP": 1, "QI0EL": 2, "QIBAJ": 3, "QIT2W": 5, "QJH8I": 2, "QJM3B": 3, "QJXNG": 1, "QK5KC": 3, "QKIYJ": 1, "QKOP0": 1, "QKP9V": 1, "QL92H": 2, "QLAS7": 2, "QLB69": 1, "QLFR5": 6, "QLGHA": 3, "QLKSV": 4, "QLWQ4": 2, "QM4AD": 2, "QMHK8": 6, "QMIKJ": 2, "QMKZV": 2, "QMTF2": 1, "QN42P": 4, "QNKDI": 2, "QNPDC": 2, "QNQOG": 1, "QNUIU": 1, "QNXGG": 1, "QO6RV": 2, "QO7SM": 1, "QOWXK": 3, "QPX3S": 1, "QQUI7": 2, "QQUU5": 1, "QQY8T": 1, "QRHJJ": 1, "QRLOG": 1, "QRM8K": 5, "QRR1S": 1, "QRSP8": 1, "QRSRE": 1, "QRWQ3": 2, "QRZK5": 5, "QS0AZ": 2, "QS6O1": 2, "QSQK2": 1, "QSSCH": 1, "QT6X8": 1, "QTGM5": 1, "QTRIN": 1, "QU2WL": 3, "QUE13": 1, "QUGLP": 1, "QUGSS": 2, "QUPLC": 1, "QVD5B": 3, "QVQNK": 2, "QWHFE": 1, "QWKVM": 4, "QX89T": 3, "QXBTG": 1, "QXCUP": 2, "QXEWB": 1, "QXEWQ": 1, "QXGK5": 1, "QXT9W": 4, "QY75H": 3, "QYE21": 1, "QYF31": 1, "QYM5H": 2, "QYPLI": 2, "QYSER": 3, "QZ94G": 4, "QZCSM": 1, "QZY6E": 1, "QZZPS": 2, "R00L7": 1, "R00LO": 2, "R0207": 4, "R0M34": 1, "R0OGE": 1, "R1DCJ": 1, "R1KMF": 2, "R1RDT": 2, "R1S1Z": 3, "R1X8P": 1, "R2DA8": 4, "R2G6S": 5, "R2KI4": 2, "R2VY3": 1, "R2YKH": 7, "R3O7U": 1, "R3ZN9": 3, "R4ENI": 2, "R4FOQ": 1, "R4SJJ": 7, "R55C1": 3, "R5K2K": 2, "R5MFX": 2, "R5WMI": 1, "R6CIX": 1, "R6H5P": 2, "R6QCQ": 1, "R7107": 1, "R74DE": 2, "R87CC": 1, "R9382": 2, "R971Z": 2, "R9NRA": 3, "RAGOI": 1, "RANB1": 3, "RAQNI": 1, "RB9VI": 2, "RBC8N": 5, "RBJ4E": 1, "RBNLA": 1, "RCD08": 2, "RDUOV": 2, "RE2CX": 1, "REOES": 3, "RF00I": 7, "RF39W": 1, "RF4OI": 1, "RFH6M": 3, "RFMRB": 1, "RG0JH": 1, "RG0KS": 2, "RG1XI": 2, "RGE8C": 2, "RGIZ7": 2, "RGNQD": 2, "RH2YW": 2, "RHAJX": 2, "RHV11": 1, "RHYAJ": 2, "RIE30": 1, "RIUEI": 2, "RIZ7Y": 3, "RJCNV": 3, "RJIEO": 1, "RJZ3I": 1, "RKGG5": 2, "RKGXU": 2, "RKJ0C": 3, "RKU88": 2, "RLA7N": 1, "RLS2I": 1, "RM1FR": 2, "RM5IC": 1, "RNCN8": 2, "RNLTR": 2, "RO116": 1, "RO429": 1, "RO9RP": 2, "RON2M": 3, "RPXAC": 2, "RPY8D": 3, "RQRRD": 2, "RR7AR": 2, "RRBM5": 1, "RRDAM": 1, "RRNDQ": 2, "RRQEV": 2, "RRZU3": 2, "RS3SQ": 1, "RS6EK": 2, "RS9D9": 1, "RSFII": 1, "RSG1C": 2, "RT1JY": 2, "RTEO8": 1, "RTEWJ": 1, "RTIP8": 2, "RUKXT": 1, "RUMS5": 2, "RV11J": 1, "RV48T": 2, "RVVDR": 3, "RVWK8": 2, "RVYXB": 2, "RX7TC": 3, "RXCQR": 2, "RXIAX": 1, "RXLKF": 3, "RXRAS": 1, "RYDUK": 1, "RYK18": 1, "RYQI0": 1, "RZ9SZ": 2, "RZIAJ": 2, "RZY2I": 1, "S027B": 1, "S0LA8": 2, "S1FYN": 2, "S1J2Q": 2, "S1LQF": 3, "S1LY3": 3, "S1PWD": 4, "S1XW9": 2, "S29H6": 1, "S2EXT": 2, "S2FLE": 1, "S2FUO": 4, "S2IG2": 3, "S2L5Z": 1, "S2RIQ": 1, "S2XJW": 3, "S3FY2": 1, "S3TZ1": 1, "S407A": 4, "S444Y": 2, "S47DI": 2, "S4EEQ": 3, "S4PLU": 1, "S4UF8": 2, "S572F": 1, "S591U": 4, "S5NC8": 2, "S673O": 2, "S6DKG": 1, "S6MPZ": 4, "S6N22": 1, "S6RYI": 2, "S7CH5": 1, "S7FHA": 2, "S7OTQ": 1, "S8PVE": 3, "S8TT8": 1, "S9P0W": 1, "S9SRM": 3, "SA7GL": 2, "SAGM9": 1, "SAIDX": 1, "SAK7K": 2, "SANRG": 4, "SBG5F": 2, "SBHID": 3, "SBOI8": 2, "SBW7O": 1, "SCOML": 1, "SCTNB": 1, "SDXZ8": 1, "SE2K2": 4, "SF6NU": 1, "SFH7G": 2, "SFHY2": 1, "SFK5D": 1, "SFOPU": 2, "SFPJ7": 3, "SG8ZR": 3, "SGAGB": 1, "SHMU7": 4, "SHP4R": 1, "SHTQ9": 1, "SHVVB": 5, "SJ4IG": 1, "SJ4QF": 1, "SJ51G": 3, "SJJ35": 5, "SJJLG": 2, "SKI92": 1, "SKZUG": 1, "SL9P2": 3, "SLAH4": 2, "SLHDI": 3, "SLMQF": 3, "SLT0S": 2, "SM41Q": 1, "SM4AO": 2, "SM5WL": 3, "SMLI0": 1, "SMMK4": 1, "SMQUM": 2, "SMS5G": 2, "SMVKB": 2, "SN85M": 1, "SNECW": 1, "SNUVF": 3, "SOR8E": 2, "SOZ1G": 1, "SP8UG": 1, "SPDF6": 3, "SPF63": 2, "SPJVR": 1, "SPKSE": 3, "SPUPH": 2, "SQ3C9": 1, "SQKE4": 2, "SQYTO": 2, "SR8IK": 4, "SRHJV": 2, "SROEU": 2, "SRQPI": 2, "SRTW8": 1, "SRTX6": 5, "SS3IL": 3, "SSH5I": 4, "SSKK6": 4, "SSPMK": 3, "STAFD": 3, "STAZI": 4, "STB0G": 2, "STDCJ": 1, "STG2D": 1, "STY6W": 1, "SU8PN": 3, "SUE5L": 3, "SUI1X": 1, "SUYMQ": 3, "SVEWD": 2, "SVIXG": 5, "SVO89": 2, "SVPZT": 2, "SVQFY": 2, "SVQL5": 1, "SW64W": 2, "SWIQN": 1, "SWYUO": 1, "SWZWL": 2, "SXFG6": 2, "SXI64": 2, "SXMII": 3, "SY1JE": 1, "SY5QP": 3, "SYMIR": 2, "SZJ09": 1, "SZYJO": 3, "T03KF": 2, "T0LOH": 1, "T0PJG": 2, "T1CQE": 2, "T1FTD": 1, "T1KK1": 3, "T2J3M": 2, "T3R3K": 5, "T42A2": 4, "T42IZ": 3, "T4NAU": 2, "T5E2T": 5, "T5JY8": 3, "T5SI3": 2, "T63X2": 2, "T6BS9": 1, "T7N6A": 3, "T7ST5": 2, "T82IE": 2, "T832F": 1, "T84EQ": 1, "T8B7B": 2, "T8O8Y": 2, "T8V10": 1, "T8XGN": 1, "T96JC": 2, "T9BED": 1, "TAGC0": 1, "TAGEG": 1, "TAGS2": 1, "TAQ25": 2, "TAZGF": 2, "TBEV0": 3, "TBRZ5": 2, "TBU3U": 1, "TBXFO": 3, "TC015": 1, "TC3BF": 1, "TCJCJ": 1, "TCN06": 2, "TCOXG": 2, "TCQ97": 1, "TD2DR": 1, "TD3HC": 1, "TD6CM": 1, "TDAY1": 2, "TDGNE": 1, "TDHM0": 1, "TDNV3": 3, "TE34B": 1, "TE421": 2, "TEPWB": 1, "TESF6": 4, "TETZ7": 1, "TEV5K": 2, "TF0KM": 4, "TF6P8": 1, "TF95Y": 1, "TF9NQ": 2, "TFCNM": 1, "TFWNO": 3, "TGDWN": 1, "TGKHG": 2, "TGUKM": 1, "TH3M0": 3, "THORO": 1, "THS0O": 1, "THW67": 4, "TI9JB": 3, "TIEA9": 2, "TIGIP": 2, "TIJOY": 2, "TIPFG": 2, "TIS3Z": 5, "TIWRY": 2, "TJBGM": 1, "TJIK7": 3, "TJJKK": 1, "TJKGJ": 4, "TJPFT": 2, "TJZ0P": 3, "TK1VC": 1, "TK76G": 1, "TKAFY": 2, "TKAUR": 3, "TKFY2": 1, "TKOYQ": 3, "TKRIZ": 1, "TKWJB": 1, "TLBWW": 2, "TLDYG": 1, "TLJRV": 4, "TLPMD": 1, "TLSUX": 1, "TM9I6": 1, "TMATS": 1, "TMTAC": 1, "TNDT2": 3, "TNEEH": 2, "TNOBD": 3, "TNWWG": 2, "TODWV": 1, "TOE9V": 1, "TOOYI": 2, "TOUXU": 2, "TOY9V": 1, "TPH12": 2, "TPHRR": 1, "TPSUY": 2, "TQ9GQ": 1, "TQGPM": 2, "TQO6O": 2, "TQXMV": 1, "TRHB9": 1, "TRHT1": 1, "TRVEA": 1, "TS2TD": 2, "TS880": 1, "TSI2S": 1, "TSYR3": 1, "TTRAJ": 2, "TTVN5": 2, "TTZVW": 3, "TU1C9": 2, "TU2GE": 1, "TU3IG": 2, "TU9K1": 2, "TUD6M": 1, "TUJF4": 1, "TUTOD": 1, "TVBLW": 1, "TVBN3": 2, "TVCQF": 1, "TVDWJ": 2, "TVJ0L": 1, "TW12W": 3, "TW2F4": 2, "TW6NZ": 2, "TWLUH": 1, "TWU2U": 1, "TWZA4": 2, "TX122": 1, "TXNDA": 2, "TXQWJ": 1, "TY68F": 3, "TYHA8": 1, "TYKVA": 1, "TYWHY": 2, "TZ27E": 1, "TZEJS": 2, "TZF0X": 1, "TZL6H": 1, "TZSIE": 2, "TZV01": 1, "TZZX3": 1, "U08M9": 1, "U0ACD": 1, "U0P7W": 4, "U0X4P": 1, "U1B27": 1, "U1BQ0": 3, "U1DE4": 3, "U1LFT": 1, "U1OYB": 1, "U2AO1": 2, "U2SJH": 3, "U33ZS": 6, "U37WC": 2, "U386F": 2, "U3ANG": 3, "U3T5A": 2, "U3VOM": 1, "U43FI": 2, "U44OC": 1, "U45LK": 2, "U4J2Q": 1, "U4W3C": 3, "U4XV9": 1, "U5M7E": 2, "U5QJR": 2, "U5RYN": 1, "U5T4M": 3, "U6L1X": 2, "U6QKX": 2, "U72GG": 1, "U75AZ": 1, "U7AAB": 2, "U7E1T": 2, "U7O1U": 3, "U91SO": 1, "U928R": 1, "U9B0R": 2, "U9KYC": 1, "U9LKA": 2, "U9NI5": 3, "U9SH3": 2, "UAIHK": 2, "UANDB": 1, "UAT1F": 3, "UB2EJ": 1, "UBC9N": 1, "UBDB5": 1, "UBUKL": 1, "UBVV7": 2, "UBYBQ": 3, "UCC1O": 1, "UCDL4": 1, "UCFCB": 1, "UCT5X": 1, "UD7R8": 2, "UDAQU": 2, "UDGP2": 2, "UDGRS": 2, "UE638": 1, "UEC1F": 1, "UEP20": 3, "UETKQ": 3, "UETQS": 2, "UEVVN": 1, "UEXO4": 1, "UF91R": 2, "UFNPU": 2, "UFQK1": 2, "UFVO8": 1, "UG4M2": 7, "UGF6Q": 2, "UGJSB": 1, "UGKZ4": 2, "UGMJZ": 2, "UGWOG": 1, "UHDEF": 2, "UI0QG": 2, "UIERL": 1, "UIHDF": 1, "UIIF3": 1, "UILMZ": 1, "UIPXF": 2, "UJJ6Z": 2, "UJO36": 2, "UJOLG": 2, "UJVCW": 1, "UKCTK": 2, "UKLQ1": 1, "UKMK6": 3, "UL5X4": 4, "UL65N": 2, "UL7YC": 6, "UL9LN": 1, "UM5II": 3, "UMOE4": 1, "UMT5R": 2, "UMXKN": 2, "UN1PD": 1, "UN86L": 1, "UNOW9": 1, "UNWMJ": 1, "UNXLF": 1, "UOI76": 1, "UOZES": 4, "UPCQK": 3, "UPUPM": 3, "UPWTC": 2, "UPXBJ": 1, "UPYPG": 1, "UQ93G": 2, "UQW95": 1, "UR55B": 4, "UR6CU": 1, "UR7C8": 2, "URG8B": 4, "URK3G": 3, "URWJL": 2, "US6P9": 1, "USM36": 2, "USNON": 1, "USNP1": 1, "USPJK": 1, "UT7R3": 1, "UTLNI": 2, "UTNL9": 2, "UU2LH": 1, "UUF84": 2, "UUPJS": 3, "UVP3F": 1, "UVPSZ": 3, "UVRMR": 3, "UWRQV": 2, "UX8NQ": 2, "UXEL9": 2, "UXET8": 2, "UXW88": 1, "UY0SK": 2, "UYJVE": 1, "UYZKX": 4, "UZ2AL": 1, "UZDEE": 1, "UZIER": 1, "UZIQS": 1, "UZMMO": 2, "UZRQD": 2, "UZTIW": 1, "V0ZD9": 1, "V10LX": 1, "V115C": 1, "V149B": 2, "V1BX9": 2, "V1JIC": 3, "V24A5": 1, "V25D1": 2, "V26U3": 2, "V2BCZ": 2, "V2C4I": 3, "V2DAA": 2, "V2MHO": 2, "V31YX": 1, "V34GF": 1, "V3CWF": 1, "V3DJ5": 2, "V3LMY": 2, "V3RAX": 2, "V3SOF": 2, "V45U8": 1, "V47ZW": 2, "V4BBC": 1, "V4C0P": 1, "V4CCY": 1, "V4HBP": 2, "V4PKW": 2, "V4YCA": 1, "V54TI": 3, "V5PK0": 1, "V62NW": 1, "V6M35": 1, "V6RRM": 2, "V70F7": 2, "V73YI": 1, "V7KBN": 1, "V7PGV": 1, "V7T91": 1, "V7YEJ": 2, "V8H9M": 2, "V8IGX": 2, "V8JOH": 1, "V9RT3": 2, "V9W9C": 3, "V9XR6": 2, "VAIVN": 2, "VAKF0": 2, "VAPVR": 1, "VAXUU": 1, "VB1HT": 2, "VCU4P": 1, "VCV6A": 2, "VCYH8": 1, "VD0H8": 3, "VD58Y": 1, "VD8PU": 3, "VE52Z": 3, "VE5DN": 2, "VE6GK": 2, "VEH0A": 1, "VEHER": 1, "VEIIK": 2, "VEKTO": 1, "VF49P": 1, "VFAE3": 2, "VFD5I": 2, "VFDQU": 2, "VG0GK": 3, "VG7S6": 1, "VG8QP": 2, "VGAMG": 2, "VGU6Y": 2, "VHD24": 3, "VHIG7": 1, "VHOYB": 1, "VICUM": 1, "VIDIE": 2, "VIN5T": 2, "VIN8S": 2, "VINM0": 2, "VJ0LT": 4, "VJ2QS": 1, "VJG6E": 2, "VJVHM": 3, "VKKIQ": 1, "VKTYD": 3, "VKXLL": 5, "VL20E": 2, "VLE11": 4, "VLYM4": 2, "VML1Z": 1, "VMOBC": 1, "VMQ20": 1, "VNMNF": 2, "VNQES": 2, "VNQJ0": 3, "VNQTH": 2, "VNVRA": 1, "VO45S": 1, "VOAAZ": 1, "VOBBG": 3, "VOTA7": 2, "VOX2S": 1, "VP3WN": 2, "VP4OG": 1, "VPB1Z": 2, "VPBIO": 2, "VQD0Z": 1, "VQOBM": 1, "VQP1L": 1, "VQWDG": 1, "VRMNI": 2, "VRXQX": 2, "VRY89": 1, "VS2RI": 1, "VS5IY": 2, "VS7DA": 2, "VS7VS": 2, "VSAA7": 2, "VSLJG": 1, "VSLQT": 4, "VSO80": 3, "VSYFA": 2, "VT624": 3, "VT64S": 2, "VTEWM": 3, "VTIUW": 2, "VTY0J": 2, "VTYXW": 2, "VU760": 2, "VU7P7": 2, "VU996": 6, "VUOQF": 1, "VUXLB": 1, "VVCK0": 2, "VVMYX": 1, "VVTJJ": 2, "VW4UD": 4, "VWAEL": 1, "VWFJA": 1, "VWN13": 1, "VX1GX": 3, "VX7P0": 2, "VX82P": 2, "VXF18": 2, "VXJS4": 1, "VXM6A": 3, "VXOE4": 1, "VXRPP": 1, "VXXOU": 1, "VYD9P": 2, "VYMZC": 1, "VYW49": 1, "VZE8E": 2, "W019T": 4, "W0A0Z": 3, "W0QSB": 1, "W0XPU": 2, "W0Y4E": 2, "W0YVE": 1, "W1SRN": 2, "W20LY": 2, "W28C2": 2, "W292V": 3, "W2DAK": 1, "W2LM5": 1, "W2QG1": 1, "W3DYV": 1, "W3I8W": 2, "W3SC3": 2, "W3Y5Q": 1, "W4MEA": 4, "W4U3V": 4, "W4WQ0": 1, "W5RC5": 2, "W5YUE": 1, "W6210": 2, "W6QUC": 2, "W6TFQ": 2, "W7CR5": 1, "W7EDM": 2, "W7EHF": 2, "W7SGQ": 3, "W86WR": 3, "W882Y": 1, "W8WRK": 2, "W8XQ9": 2, "W97NR": 3, "W9HYI": 1, "W9XJX": 1, "W9XY8": 1, "WA7WD": 5, "WAOE7": 1, "WB17C": 2, "WBATR": 2, "WBBTU": 1, "WBS4I": 2, "WC5QK": 3, "WCCY7": 2, "WCERV": 2, "WCLGY": 1, "WCY52": 1, "WD12X": 2, "WD6WB": 1, "WDB4S": 1, "WDCGH": 3, "WDF45": 1, "WE2PF": 4, "WEIJ6": 1, "WEJRX": 1, "WENGZ": 2, "WESPT": 1, "WEW2E": 3, "WEYV3": 4, "WFD5Z": 4, "WGFU7": 1, "WGM7C": 1, "WGZ29": 3, "WH1PD": 2, "WH1S5": 1, "WHJ70": 1, "WI6NB": 2, "WIOOY": 1, "WIUQN": 2, "WIYE2": 3, "WJ1E7": 2, "WJ1GN": 2, "WJ33D": 1, "WJEVU": 6, "WK5PL": 1, "WK9HE": 4, "WKDPZ": 1, "WKP5N": 4, "WKPQ3": 2, "WKVWF": 2, "WLA52": 2, "WLE0F": 1, "WM2J7": 3, "WM336": 2, "WM6RQ": 2, "WM8QQ": 3, "WMR4G": 1, "WN2N7": 1, "WN38A": 1, "WN7T3": 1, "WNW0S": 1, "WO0OM": 2, "WOD0G": 3, "WOVOX": 1, "WP5RH": 1, "WP8D0": 3, "WPPAT": 1, "WPR8G": 1, "WPRJD": 3, "WPU76": 4, "WQ57B": 1, "WQQ4Q": 2, "WQWT0": 3, "WR1QE": 1, "WR2Q2": 1, "WRCO6": 1, "WREDC": 2, "WRFZW": 5, "WRW74": 1, "WRW7O": 1, "WRXI4": 1, "WSB7W": 1, "WSKTN": 1, "WSLMS": 1, "WSS0V": 1, "WSZSL": 1, "WT405": 2, "WT46G": 5, "WT59C": 2, "WTFOC": 1, "WTGVG": 2, "WTIQ3": 2, "WTJQ0": 2, "WTMMC": 1, "WTPQ6": 1, "WTU0I": 4, "WTUGM": 1, "WUTHF": 1, "WV8SY": 1, "WV9FZ": 3, "WVB7F": 1, "WVOQP": 3, "WW4MY": 2, "WWPEN": 2, "WX7AG": 2, "WX8N8": 3, "WXBEO": 2, "WXGLA": 1, "WXMTI": 1, "WXUZK": 1, "WXXYY": 2, "WYCRK": 2, "WYM1M": 1, "WYYUD": 2, "WYZCW": 2, "WZCPT": 1, "WZDXS": 5, "WZN0I": 1, "WZVHJ": 2, "WZY7C": 1, "X06Z6": 2, "X07QW": 2, "X084M": 1, "X0CVU": 4, "X0FW6": 1, "X11CU": 3, "X1EZQ": 2, "X1KKZ": 1, "X226B": 1, "X28IF": 4, "X29NF": 5, "X2LBW": 8, "X2Q00": 4, "X3ASU": 3, "X3EZR": 1, "X3FAP": 2, "X3LEM": 2, "X42YA": 1, "X4BQG": 2, "X4CZH": 1, "X4DG4": 1, "X4DOF": 1, "X4WWH": 3, "X4YHQ": 3, "X58SH": 2, "X5E6E": 2, "X5QMG": 2, "X5YL3": 2, "X62WQ": 2, "X6B0P": 2, "X7J7H": 2, "X7QXE": 1, "X817Z": 3, "X89FW": 2, "X8A6H": 1, "X8AP2": 1, "X8DZV": 3, "X8JVY": 4, "X8LT0": 2, "X8XQE": 2, "X91NG": 2, "X95FK": 1, "X9LP4": 2, "X9Q1A": 1, "X9WTR": 5, "XAOUP": 3, "XAX61": 1, "XB4HN": 2, "XBB9P": 1, "XBTN7": 1, "XBXKO": 1, "XC8DF": 1, "XC9EY": 1, "XDS14": 4, "XDT45": 1, "XDVAY": 2, "XE4FF": 1, "XF41L": 3, "XFLQH": 3, "XFRYR": 1, "XFS7Z": 2, "XG839": 3, "XGS3K": 2, "XHG13": 1, "XHL3Z": 3, "XHN6Y": 2, "XI9LI": 1, "XIG01": 1, "XIUJE": 1, "XIUQJ": 3, "XIYIK": 1, "XJ4T3": 2, "XJA7Z": 2, "XJE4Y": 2, "XJFMW": 1, "XJH0X": 1, "XJH5D": 2, "XJLHC": 1, "XJOJL": 1, "XJU8U": 1, "XK92L": 1, "XKJAD": 2, "XKU2U": 2, "XLH1M": 1, "XLQ6X": 1, "XLR4B": 3, "XMF8Y": 4, "XMI29": 3, "XMYXI": 3, "XNBUT": 1, "XNT6F": 1, "XNXW6": 1, "XNYAH": 2, "XO8NL": 2, "XO97L": 2, "XOOPP": 1, "XOOTA": 1, "XOWBN": 2, "XP305": 1, "XPDI1": 2, "XPOKK": 2, "XPWYQ": 1, "XQC9F": 1, "XQDQ4": 1, "XQWLY": 1, "XRG9K": 2, "XRMVW": 1, "XRR22": 1, "XRWBL": 2, "XS6PF": 2, "XS7RN": 2, "XSBZ1": 1, "XSGYC": 5, "XSRBI": 1, "XSS0J": 1, "XSVLL": 1, "XT9D4": 5, "XTHL8": 1, "XTRH7": 1, "XUV0Y": 2, "XVHGO": 3, "XVI3M": 2, "XVNJC": 4, "XW1LX": 1, "XWKKZ": 1, "XWQ3Z": 1, "XWVDK": 1, "XX3RB": 2, "XXDHJ": 1, "XXIT4": 2, "XXMN1": 2, "XXS99": 2, "XXU6H": 1, "XXX1O": 3, "XXYWL": 1, "XY2M3": 1, "XY4C7": 1, "XYGU1": 3, "XZ2WT": 4, "XZ9C0": 1, "XZM6Y": 1, "Y05U8": 2, "Y0CA0": 1, "Y0MCG": 1, "Y1BWP": 1, "Y1HOV": 2, "Y2DK5": 3, "Y2EID": 1, "Y2MGC": 4, "Y2QUJ": 1, "Y3M3W": 2, "Y4LT8": 2, "Y4MW3": 2, "Y4P3C": 1, "Y4X8J": 2, "Y5ZU3": 1, "Y665P": 2, "Y6MUU": 4, "Y6P1E": 1, "Y6ROG": 2, "Y6ZJI": 2, "Y79PC": 1, "Y7CGN": 2, "Y7WEK": 1, "Y80PJ": 2, "Y89SO": 2, "Y8ON2": 1, "Y9930": 1, "Y9JWG": 1, "Y9SMX": 2, "Y9WZW": 3, "YACA8": 2, "YAFX0": 2, "YAPN7": 4, "YAXGX": 1, "YB67Z": 2, "YBVVZ": 3, "YBXCT": 1, "YC3OE": 4, "YC9FL": 1, "YCGJS": 3, "YCST7": 1, "YD8BF": 2, "YDTH0": 2, "YDWN5": 2, "YE47Y": 5, "YE6UZ": 2, "YE991": 1, "YEHFQ": 1, "YFBA1": 1, "YFH0D": 1, "YFI1M": 1, "YFPHS": 2, "YGL6R": 4, "YGQ7E": 1, "YH0BX": 1, "YH70K": 2, "YH7K4": 3, "YHFKO": 1, "YHPLU": 2, "YHXU9": 1, "YIG5G": 8, "YIIFF": 2, "YIK5I": 4, "YINV4": 1, "YIV35": 3, "YJ06D": 1, "YJ1KW": 5, "YJQO3": 1, "YJRBY": 1, "YJV3E": 1, "YLE12": 2, "YLEK5": 1, "YLGF5": 1, "YLRVT": 1, "YMD74": 2, "YMGGV": 1, "YMJ6E": 1, "YMM1Z": 1, "YNCFL": 2, "YNF6O": 1, "YNIWQ": 3, "YNJ86": 1, "YNRI0": 2, "YNWMW": 3, "YO3KO": 2, "YO9NC": 3, "YOCI8": 2, "YOCRB": 3, "YONR1": 2, "YOVS5": 1, "YP1HM": 4, "YPIKO": 3, "YPQ97": 1, "YPRUL": 2, "YPTDT": 1, "YPUYO": 1, "YPZQ2": 1, "YQ2M5": 1, "YQ6Z6": 1, "YQCYJ": 3, "YQOPM": 1, "YQT32": 1, "YRPAR": 1, "YRX5H": 2, "YSABV": 1, "YSBN0": 1, "YSKX3": 1, "YSL3Z": 2, "YT3VH": 1, "YTV2H": 2, "YUCU2": 2, "YUEB9": 4, "YUOVC": 1, "YUTDC": 2, "YV521": 3, "YVH4J": 3, "YVK8M": 1, "YVKIV": 2, "YVOVB": 2, "YW5C4": 1, "YW5QQ": 3, "YX3V0": 2, "YXC7P": 1, "YXJBA": 5, "YXQWH": 1, "YXSI7": 1, "YYGJV": 1, "YYHX3": 1, "YYLKT": 3, "YZ8HK": 1, "YZI2P": 1, "Z04NK": 1, "Z06HO": 2, "Z0DO7": 3, "Z0O2V": 1, "Z0Q5D": 1, "Z1DBB": 1, "Z1LE8": 3, "Z1LVD": 1, "Z1VB4": 2, "Z1ZUI": 1, "Z2A7Q": 1, "Z2DEZ": 1, "Z2MY2": 1, "Z320B": 2, "Z3AGB": 3, "Z3DBQ": 1, "Z3H4P": 3, "Z4P5B": 2, "Z4Y02": 1, "Z4Y04": 2, "Z5AZW": 1, "Z5THW": 1, "Z5URX": 8, "Z6HEA": 2, "Z6HSZ": 2, "Z6LYG": 1, "Z6OEM": 1, "Z6U1X": 2, "Z6ZYF": 2, "Z70KK": 1, "Z7KC1": 2, "Z7O9G": 2, "Z7QTA": 2, "Z7UOT": 3, "Z8HPQ": 1, "Z97SD": 2, "Z9B4Y": 2, "Z9THH": 1, "Z9W47": 1, "Z9WWJ": 1, "Z9XLJ": 2, "ZA7ST": 1, "ZAJAJ": 3, "ZAJYX": 1, "ZAN58": 1, "ZATTZ": 1, "ZB5J4": 2, "ZC017": 4, "ZC8L5": 1, "ZCG3J": 2, "ZCH1J": 2, "ZCH7N": 4, "ZCPG6": 1, "ZCULX": 2, "ZD3GI": 5, "ZDFOL": 2, "ZDV60": 1, "ZDWM7": 1, "ZDZFF": 1, "ZED9E": 1, "ZF5CP": 2, "ZFQNZ": 1, "ZFT06": 2, "ZFT87": 3, "ZFZEN": 3, "ZG1EM": 1, "ZGHLY": 1, "ZH4JE": 1, "ZHDUR": 2, "ZHF60": 1, "ZHOP3": 3, "ZHRPD": 3, "ZI1GC": 3, "ZI2XH": 2, "ZI3ED": 1, "ZIP18": 3, "ZIU9C": 2, "ZIWZH": 1, "ZJ54N": 2, "ZJPK8": 2, "ZJRCS": 3, "ZKGKR": 2, "ZKNHG": 2, "ZKSR1": 1, "ZL55N": 1, "ZLH9E": 2, "ZLWXE": 2, "ZMY8M": 3, "ZNH10": 2, "ZNQVC": 4, "ZO3EG": 3, "ZOBZV": 1, "ZOK5T": 1, "ZOL0R": 1, "ZOLVU": 3, "ZOMM2": 2, "ZOTR8": 1, "ZP4X6": 1, "ZP53M": 4, "ZP8AL": 1, "ZPNW7": 2, "ZPRJH": 2, "ZPUVC": 2, "ZQAMW": 1, "ZQKVY": 1, "ZR19K": 1, "ZRRC8": 1, "ZS2WD": 1, "ZS66D": 2, "ZS9XR": 4, "ZSJ2I": 3, "ZSREG": 1, "ZSZS4": 2, "ZTWJB": 3, "ZU8Q1": 4, "ZUU2X": 2, "ZVCMM": 2, "ZVRBL": 1, "ZVV1Y": 2, "ZWDVG": 3, "ZWE6N": 2, "ZWPS3": 4, "ZWY3E": 1, "ZX1R7": 1, "ZX37G": 2, "ZXHCH": 2, "ZXKUH": 1, "ZXN6A": 4, "ZXSRR": 3, "ZY2B1": 2, "ZYZWX": 2, "ZZ2SF": 1, "ZZ3HT": 1, "ZZ89F": 2, "ZZ9RN": 1, "ZZXQF": 1}